<BodyGesture Name="hands up" Postures="23">
	<BodyPosture Time="41106934.2628" Joints="20">
		<Joint Type="HipCenter" X="0.0179437361657619" Y="0.125158339738846" Z="2.8297655582428" />
		<Joint Type="Spine" X="0.0145926885306835" Y="0.169922456145287" Z="2.87550973892212" />
		<Joint Type="ShoulderCenter" X="0.0111617092043161" Y="0.448721289634705" Z="2.90035581588745" />
		<Joint Type="Head" X="0.0064325388520956" Y="0.589927136898041" Z="2.88495850563049" />
		<Joint Type="ShoulderLeft" X="-0.102302335202694" Y="0.344217658042908" Z="2.87473773956299" />
		<Joint Type="ElbowLeft" X="-0.125258192420006" Y="0.147997498512268" Z="2.82660961151123" />
		<Joint Type="WristLeft" X="-0.129498094320297" Y="-0.00702908635139465" Z="2.7665855884552" />
		<Joint Type="HandLeft" X="-0.129466682672501" Y="-0.0466541312634945" Z="2.76914095878601" />
		<Joint Type="ShoulderRight" X="0.118390306830406" Y="0.348909080028534" Z="2.88848185539246" />
		<Joint Type="ElbowRight" X="0.142307236790657" Y="0.158114597201347" Z="2.86126446723938" />
		<Joint Type="WristRight" X="0.140232354402542" Y="-0.0087724095210433" Z="2.79825329780579" />
		<Joint Type="HandRight" X="0.126515001058578" Y="-0.0227629113942385" Z="2.76114964485168" />
		<Joint Type="HipLeft" X="-0.0298634190112352" Y="0.0760982260107994" Z="2.81566834449768" />
		<Joint Type="KneeLeft" X="-0.0275372955948114" Y="-0.205035910010338" Z="2.84466195106506" />
		<Joint Type="AnkleLeft" X="-0.0442363172769547" Y="-0.425465732812881" Z="2.82603931427002" />
		<Joint Type="FootLeft" X="-0.047444574534893" Y="-0.473142981529236" Z="2.79390978813171" />
		<Joint Type="HipRight" X="0.068404033780098" Y="0.0780849903821945" Z="2.82016968727112" />
		<Joint Type="KneeRight" X="0.0532270260155201" Y="-0.197737187147141" Z="2.84078073501587" />
		<Joint Type="AnkleRight" X="0.0595685541629791" Y="-0.421842336654663" Z="2.81561160087585" />
		<Joint Type="FootRight" X="0.0592620261013508" Y="-0.470213562250137" Z="2.78302216529846" />
	</BodyPosture>
	<BodyPosture Time="41107060.2701" Joints="20">
		<Joint Type="HipCenter" X="0.0175303611904383" Y="0.124611660838127" Z="2.82879495620728" />
		<Joint Type="Spine" X="0.0142899062484503" Y="0.169651985168457" Z="2.87451767921448" />
		<Joint Type="ShoulderCenter" X="0.0115932133048773" Y="0.448091953992844" Z="2.89744734764099" />
		<Joint Type="Head" X="0.00652050133794546" Y="0.588006138801575" Z="2.88392210006714" />
		<Joint Type="ShoulderLeft" X="-0.102176330983639" Y="0.343957036733627" Z="2.87393498420715" />
		<Joint Type="ElbowLeft" X="-0.125623553991318" Y="0.146169424057007" Z="2.82267165184021" />
		<Joint Type="WristLeft" X="-0.131447419524193" Y="-0.00958502292633057" Z="2.7651219367981" />
		<Joint Type="HandLeft" X="-0.132747039198875" Y="-0.045461367815733" Z="2.76413011550903" />
		<Joint Type="ShoulderRight" X="0.118270576000214" Y="0.34832501411438" Z="2.88798952102661" />
		<Joint Type="ElbowRight" X="0.141466751694679" Y="0.157653883099556" Z="2.85774779319763" />
		<Joint Type="WristRight" X="0.139683336019516" Y="-0.00970871932804585" Z="2.79677820205688" />
		<Joint Type="HandRight" X="0.124703243374825" Y="-0.0182995293289423" Z="2.75704479217529" />
		<Joint Type="HipLeft" X="-0.0304704010486603" Y="0.0756927952170372" Z="2.8144690990448" />
		<Joint Type="KneeLeft" X="-0.0282265432178974" Y="-0.20490226149559" Z="2.84463167190552" />
		<Joint Type="AnkleLeft" X="-0.0455138869583607" Y="-0.424204260110855" Z="2.82717084884644" />
		<Joint Type="FootLeft" X="-0.0472604744136333" Y="-0.473237186670303" Z="2.79252791404724" />
		<Joint Type="HipRight" X="0.0677167102694511" Y="0.0773937851190567" Z="2.81938219070435" />
		<Joint Type="KneeRight" X="0.0516592860221863" Y="-0.197702616453171" Z="2.83986449241638" />
		<Joint Type="AnkleRight" X="0.0563352890312672" Y="-0.42198657989502" Z="2.81649565696716" />
		<Joint Type="FootRight" X="0.0589001700282097" Y="-0.470591485500336" Z="2.78277611732483" />
	</BodyPosture>
	<BodyPosture Time="41107216.2703" Joints="20">
		<Joint Type="HipCenter" X="0.0177356638014317" Y="0.123785547912121" Z="2.82708764076233" />
		<Joint Type="Spine" X="0.0143142808228731" Y="0.168904408812523" Z="2.87312126159668" />
		<Joint Type="ShoulderCenter" X="0.0115216877311468" Y="0.447902739048004" Z="2.89674854278564" />
		<Joint Type="Head" X="0.00903767067939043" Y="0.586545944213867" Z="2.88254928588867" />
		<Joint Type="ShoulderLeft" X="-0.102106295526028" Y="0.34366163611412" Z="2.87234544754028" />
		<Joint Type="ElbowLeft" X="-0.126901537179947" Y="0.146639034152031" Z="2.81838488578796" />
		<Joint Type="WristLeft" X="-0.132194548845291" Y="-0.00998601317405701" Z="2.76371359825134" />
		<Joint Type="HandLeft" X="-0.134145438671112" Y="-0.0471923388540745" Z="2.75985193252563" />
		<Joint Type="ShoulderRight" X="0.118909798562527" Y="0.347505450248718" Z="2.88730692863464" />
		<Joint Type="ElbowRight" X="0.14175671339035" Y="0.158035144209862" Z="2.85708045959473" />
		<Joint Type="WristRight" X="0.140027731657028" Y="-0.0110731162130833" Z="2.79594492912292" />
		<Joint Type="HandRight" X="0.125993281602859" Y="-0.0262437500059605" Z="2.75799036026001" />
		<Joint Type="HipLeft" X="-0.0303385108709335" Y="0.0748704001307487" Z="2.81228613853455" />
		<Joint Type="KneeLeft" X="-0.0285994485020638" Y="-0.206715375185013" Z="2.84456253051758" />
		<Joint Type="AnkleLeft" X="-0.0475664064288139" Y="-0.425860077142715" Z="2.82731008529663" />
		<Joint Type="FootLeft" X="-0.0498997643589973" Y="-0.473774969577789" Z="2.79220509529114" />
		<Joint Type="HipRight" X="0.0679982751607895" Y="0.0763099566102028" Z="2.81753444671631" />
		<Joint Type="KneeRight" X="0.0503557510674" Y="-0.197217136621475" Z="2.8390839099884" />
		<Joint Type="AnkleRight" X="0.0549689196050167" Y="-0.421496450901031" Z="2.81597018241882" />
		<Joint Type="FootRight" X="0.0593681149184704" Y="-0.469983011484146" Z="2.78202652931213" />
	</BodyPosture>
	<BodyPosture Time="41107294.2705" Joints="20">
		<Joint Type="HipCenter" X="0.0176705438643694" Y="0.124572589993477" Z="2.82454657554626" />
		<Joint Type="Spine" X="0.0132698649540544" Y="0.16980741918087" Z="2.87029647827148" />
		<Joint Type="ShoulderCenter" X="0.0109302485361695" Y="0.447497874498367" Z="2.89174842834473" />
		<Joint Type="Head" X="0.00993571523576975" Y="0.588001132011414" Z="2.88229322433472" />
		<Joint Type="ShoulderLeft" X="-0.101718589663506" Y="0.344040095806122" Z="2.86921668052673" />
		<Joint Type="ElbowLeft" X="-0.148955747485161" Y="0.172114253044128" Z="2.7793083190918" />
		<Joint Type="WristLeft" X="-0.169826626777649" Y="0.0302786082029343" Z="2.69178223609924" />
		<Joint Type="HandLeft" X="-0.185166984796524" Y="-0.00340605899691582" Z="2.64875864982605" />
		<Joint Type="ShoulderRight" X="0.120174996554852" Y="0.348237752914429" Z="2.88999223709106" />
		<Joint Type="ElbowRight" X="0.187891080975533" Y="0.179157391190529" Z="2.83500385284424" />
		<Joint Type="WristRight" X="0.164088770747185" Y="0.0368483513593674" Z="2.74921178817749" />
		<Joint Type="HandRight" X="0.165570005774498" Y="0.000468015670776367" Z="2.72838020324707" />
		<Joint Type="HipLeft" X="-0.0305759571492672" Y="0.0756223127245903" Z="2.80879831314087" />
		<Joint Type="KneeLeft" X="-0.0290602203458548" Y="-0.207449600100517" Z="2.84442591667175" />
		<Joint Type="AnkleLeft" X="-0.0482672564685345" Y="-0.425434172153473" Z="2.82821178436279" />
		<Joint Type="FootLeft" X="-0.0478463508188725" Y="-0.473937213420868" Z="2.79220342636108" />
		<Joint Type="HipRight" X="0.0680640339851379" Y="0.0765458792448044" Z="2.81589674949646" />
		<Joint Type="KneeRight" X="0.0516890361905098" Y="-0.197416812181473" Z="2.83807229995728" />
		<Joint Type="AnkleRight" X="0.0574588850140572" Y="-0.42125678062439" Z="2.81501984596252" />
		<Joint Type="FootRight" X="0.0596652813255787" Y="-0.469984322786331" Z="2.78222608566284" />
	</BodyPosture>
	<BodyPosture Time="41107387.8706" Joints="20">
		<Joint Type="HipCenter" X="0.0173530299216509" Y="0.124790176749229" Z="2.82467412948608" />
		<Joint Type="Spine" X="0.0132883284240961" Y="0.168718740344048" Z="2.8707115650177" />
		<Joint Type="ShoulderCenter" X="0.0124469911679626" Y="0.448029935359955" Z="2.90480804443359" />
		<Joint Type="Head" X="0.00938186980783939" Y="0.587860703468323" Z="2.88260817527771" />
		<Joint Type="ShoulderLeft" X="-0.101244106888771" Y="0.343971133232117" Z="2.86936640739441" />
		<Joint Type="ElbowLeft" X="-0.191029861569405" Y="0.273230105638504" Z="2.71881484985352" />
		<Joint Type="WristLeft" X="-0.250295579433441" Y="0.203304708003998" Z="2.57402491569519" />
		<Joint Type="HandLeft" X="-0.255661249160767" Y="0.195168569684029" Z="2.56341481208801" />
		<Joint Type="ShoulderRight" X="0.122548960149288" Y="0.351596653461456" Z="2.88969326019287" />
		<Joint Type="ElbowRight" X="0.248805463314056" Y="0.291131913661957" Z="2.78651762008667" />
		<Joint Type="WristRight" X="0.251145035028458" Y="0.210720211267471" Z="2.63474202156067" />
		<Joint Type="HandRight" X="0.252233237028122" Y="0.189200311899185" Z="2.61555671691895" />
		<Joint Type="HipLeft" X="-0.0312572531402111" Y="0.0758770331740379" Z="2.80871891975403" />
		<Joint Type="KneeLeft" X="-0.0283655244857073" Y="-0.204196810722351" Z="2.84440779685974" />
		<Joint Type="AnkleLeft" X="-0.045451857149601" Y="-0.42566579580307" Z="2.82570195198059" />
		<Joint Type="FootLeft" X="-0.0473010987043381" Y="-0.473212689161301" Z="2.79399728775024" />
		<Joint Type="HipRight" X="0.067647248506546" Y="0.0768322125077248" Z="2.81548094749451" />
		<Joint Type="KneeRight" X="0.0514101609587669" Y="-0.196097820997238" Z="2.83739399909973" />
		<Joint Type="AnkleRight" X="0.0599102787673473" Y="-0.420182228088379" Z="2.81502175331116" />
		<Joint Type="FootRight" X="0.0587487258017063" Y="-0.470146238803864" Z="2.78003907203674" />
	</BodyPosture>
	<BodyPosture Time="41107543.8709" Joints="20">
		<Joint Type="HipCenter" X="0.0147506408393383" Y="0.131727635860443" Z="2.82408738136292" />
		<Joint Type="Spine" X="0.0124039426445961" Y="0.172986447811127" Z="2.87138938903809" />
		<Joint Type="ShoulderCenter" X="0.0157146528363228" Y="0.448030173778534" Z="2.9095242023468" />
		<Joint Type="Head" X="0.0093312868848443" Y="0.588758707046509" Z="2.88333535194397" />
		<Joint Type="ShoulderLeft" X="-0.101370185613632" Y="0.35528975725174" Z="2.87348556518555" />
		<Joint Type="ElbowLeft" X="-0.209051176905632" Y="0.380598187446594" Z="2.71969056129456" />
		<Joint Type="WristLeft" X="-0.28672468662262" Y="0.407107889652252" Z="2.56888246536255" />
		<Joint Type="HandLeft" X="-0.301226168870926" Y="0.415183544158936" Z="2.55035519599915" />
		<Joint Type="ShoulderRight" X="0.129161506891251" Y="0.361604660749435" Z="2.89184617996216" />
		<Joint Type="ElbowRight" X="0.26600855588913" Y="0.384758144617081" Z="2.78674507141113" />
		<Joint Type="WristRight" X="0.28181004524231" Y="0.419761329889297" Z="2.61834144592285" />
		<Joint Type="HandRight" X="0.285505145788193" Y="0.434075742959976" Z="2.5635347366333" />
		<Joint Type="HipLeft" X="-0.0356220714747906" Y="0.0821356847882271" Z="2.80627417564392" />
		<Joint Type="KneeLeft" X="-0.0287892669439316" Y="-0.202880218625069" Z="2.84417343139648" />
		<Joint Type="AnkleLeft" X="-0.0462552048265934" Y="-0.425553470849991" Z="2.82422709465027" />
		<Joint Type="FootLeft" X="-0.0480147115886211" Y="-0.471954703330994" Z="2.79512095451355" />
		<Joint Type="HipRight" X="0.0647246539592743" Y="0.0828289166092873" Z="2.81268382072449" />
		<Joint Type="KneeRight" X="0.0528156794607639" Y="-0.195369258522987" Z="2.83715343475342" />
		<Joint Type="AnkleRight" X="0.0597061775624752" Y="-0.420319944620132" Z="2.81544232368469" />
		<Joint Type="FootRight" X="0.0575593486428261" Y="-0.46990031003952" Z="2.78082251548767" />
	</BodyPosture>
	<BodyPosture Time="41107715.4712" Joints="20">
		<Joint Type="HipCenter" X="0.0178223811089993" Y="0.156426176428795" Z="2.82029891014099" />
		<Joint Type="Spine" X="0.0135046308860183" Y="0.19233250617981" Z="2.8677442073822" />
		<Joint Type="ShoulderCenter" X="0.0151873473078012" Y="0.448581874370575" Z="2.90630197525024" />
		<Joint Type="Head" X="0.0102202985435724" Y="0.588595509529114" Z="2.88100099563599" />
		<Joint Type="ShoulderLeft" X="-0.101594313979149" Y="0.380079627037048" Z="2.87625741958618" />
		<Joint Type="ElbowLeft" X="-0.210347965359688" Y="0.516451001167297" Z="2.75248622894287" />
		<Joint Type="WristLeft" X="-0.269515812397003" Y="0.636390388011932" Z="2.64943194389343" />
		<Joint Type="HandLeft" X="-0.264833122491837" Y="0.652040481567383" Z="2.66111040115356" />
		<Joint Type="ShoulderRight" X="0.135830625891685" Y="0.394131869077683" Z="2.90509438514709" />
		<Joint Type="ElbowRight" X="0.237384036183357" Y="0.524427175521851" Z="2.82941222190857" />
		<Joint Type="WristRight" X="0.258861809968948" Y="0.649128019809723" Z="2.71676778793335" />
		<Joint Type="HandRight" X="0.254307955503464" Y="0.668620407581329" Z="2.72638988494873" />
		<Joint Type="HipLeft" X="-0.0317082293331623" Y="0.106967195868492" Z="2.7985692024231" />
		<Joint Type="KneeLeft" X="-0.0257590860128403" Y="-0.197390481829643" Z="2.842613697052" />
		<Joint Type="AnkleLeft" X="-0.0447281375527382" Y="-0.425546884536743" Z="2.82436418533325" />
		<Joint Type="FootLeft" X="-0.0459992997348309" Y="-0.472030371427536" Z="2.7933976650238" />
		<Joint Type="HipRight" X="0.0692392736673355" Y="0.104585826396942" Z="2.80880403518677" />
		<Joint Type="KneeRight" X="0.052283301949501" Y="-0.194108992815018" Z="2.83761787414551" />
		<Joint Type="AnkleRight" X="0.0559266097843647" Y="-0.420821845531464" Z="2.81439137458801" />
		<Joint Type="FootRight" X="0.0580376721918583" Y="-0.469270646572113" Z="2.78098082542419" />
	</BodyPosture>
	<BodyPosture Time="41107793.4713" Joints="20">
		<Joint Type="HipCenter" X="0.0246359053999186" Y="0.179352328181267" Z="2.81786847114563" />
		<Joint Type="Spine" X="0.0176816135644913" Y="0.212123811244965" Z="2.86367130279541" />
		<Joint Type="ShoulderCenter" X="0.00871176086366177" Y="0.448129117488861" Z="2.89021682739258" />
		<Joint Type="Head" X="0.0090591674670577" Y="0.586330652236938" Z="2.87453579902649" />
		<Joint Type="ShoulderLeft" X="-0.103759534657001" Y="0.392713844776154" Z="2.87907838821411" />
		<Joint Type="ElbowLeft" X="-0.194095611572266" Y="0.538943111896515" Z="2.79130864143372" />
		<Joint Type="WristLeft" X="-0.23403924703598" Y="0.690676093101501" Z="2.73755645751953" />
		<Joint Type="HandLeft" X="-0.243680238723755" Y="0.72836434841156" Z="2.74017214775085" />
		<Joint Type="ShoulderRight" X="0.133753567934036" Y="0.418911039829254" Z="2.91616177558899" />
		<Joint Type="ElbowRight" X="0.220989942550659" Y="0.601191341876984" Z="2.85795331001282" />
		<Joint Type="WristRight" X="0.234275847673416" Y="0.751866579055786" Z="2.78748321533203" />
		<Joint Type="HandRight" X="0.23623326420784" Y="0.808364629745483" Z="2.792640209198" />
		<Joint Type="HipLeft" X="-0.023504089564085" Y="0.126085698604584" Z="2.7937536239624" />
		<Joint Type="KneeLeft" X="-0.0237165931612253" Y="-0.191192537546158" Z="2.83775448799133" />
		<Joint Type="AnkleLeft" X="-0.0386359691619873" Y="-0.425934493541718" Z="2.82327270507813" />
		<Joint Type="FootLeft" X="-0.0424242578446865" Y="-0.472611427307129" Z="2.77992391586304" />
		<Joint Type="HipRight" X="0.0782780945301056" Y="0.128658682107925" Z="2.80958127975464" />
		<Joint Type="KneeRight" X="0.0523974634706974" Y="-0.191322267055511" Z="2.83548760414124" />
		<Joint Type="AnkleRight" X="0.0537854507565498" Y="-0.420006632804871" Z="2.81488013267517" />
		<Joint Type="FootRight" X="0.0526133254170418" Y="-0.467255800962448" Z="2.77252388000488" />
	</BodyPosture>
	<BodyPosture Time="41107949.4716" Joints="20">
		<Joint Type="HipCenter" X="0.0239556729793549" Y="0.183668076992035" Z="2.8175482749939" />
		<Joint Type="Spine" X="0.01694505661726" Y="0.216370090842247" Z="2.86278367042542" />
		<Joint Type="ShoulderCenter" X="0.00692458730190992" Y="0.449105560779572" Z="2.88628244400024" />
		<Joint Type="Head" X="0.00893393345177174" Y="0.586690366268158" Z="2.87351489067078" />
		<Joint Type="ShoulderLeft" X="-0.101361371576786" Y="0.396211177110672" Z="2.88159275054932" />
		<Joint Type="ElbowLeft" X="-0.189175546169281" Y="0.551448822021484" Z="2.80885124206543" />
		<Joint Type="WristLeft" X="-0.227446869015694" Y="0.705479443073273" Z="2.76222515106201" />
		<Joint Type="HandLeft" X="-0.241400733590126" Y="0.759705185890198" Z="2.75280261039734" />
		<Joint Type="ShoulderRight" X="0.131091356277466" Y="0.422558069229126" Z="2.91731190681458" />
		<Joint Type="ElbowRight" X="0.21783809363842" Y="0.604770064353943" Z="2.85937643051147" />
		<Joint Type="WristRight" X="0.230874359607697" Y="0.762120842933655" Z="2.80933737754822" />
		<Joint Type="HandRight" X="0.235293567180634" Y="0.817365407943726" Z="2.82168388366699" />
		<Joint Type="HipLeft" X="-0.0229059811681509" Y="0.131556823849678" Z="2.79477596282959" />
		<Joint Type="KneeLeft" X="-0.0236112121492624" Y="-0.189945384860039" Z="2.83721899986267" />
		<Joint Type="AnkleLeft" X="-0.04063605889678" Y="-0.425693899393082" Z="2.8223922252655" />
		<Joint Type="FootLeft" X="-0.0368505567312241" Y="-0.472830325365067" Z="2.77945399284363" />
		<Joint Type="HipRight" X="0.0769361108541489" Y="0.134786054491997" Z="2.80958700180054" />
		<Joint Type="KneeRight" X="0.0531838163733482" Y="-0.188958555459976" Z="2.83443331718445" />
		<Joint Type="AnkleRight" X="0.0526593029499054" Y="-0.420199513435364" Z="2.81502079963684" />
		<Joint Type="FootRight" X="0.0548308789730072" Y="-0.468930959701538" Z="2.77420282363892" />
	</BodyPosture>
	<BodyPosture Time="41108105.4719" Joints="20">
		<Joint Type="HipCenter" X="0.0242369286715984" Y="0.194716781377792" Z="2.81952428817749" />
		<Joint Type="Spine" X="0.0186981931328774" Y="0.225141331553459" Z="2.86443114280701" />
		<Joint Type="ShoulderCenter" X="0.00603051111102104" Y="0.449099123477936" Z="2.88685774803162" />
		<Joint Type="Head" X="0.0108695523813367" Y="0.581946730613709" Z="2.86882281303406" />
		<Joint Type="ShoulderLeft" X="-0.0960722267627716" Y="0.41699630022049" Z="2.89516639709473" />
		<Joint Type="ElbowLeft" X="-0.183569088578224" Y="0.562134146690369" Z="2.82842206954956" />
		<Joint Type="WristLeft" X="-0.223464339971542" Y="0.720008552074432" Z="2.81557059288025" />
		<Joint Type="HandLeft" X="-0.235328033566475" Y="0.774829089641571" Z="2.8246066570282" />
		<Joint Type="ShoulderRight" X="0.126696467399597" Y="0.43436872959137" Z="2.91760540008545" />
		<Joint Type="ElbowRight" X="0.209931612014771" Y="0.613297462463379" Z="2.87399339675903" />
		<Joint Type="WristRight" X="0.229623198509216" Y="0.773205637931824" Z="2.84011673927307" />
		<Joint Type="HandRight" X="0.237397640943527" Y="0.826997756958008" Z="2.85665917396545" />
		<Joint Type="HipLeft" X="-0.0213854722678661" Y="0.145240768790245" Z="2.80004096031189" />
		<Joint Type="KneeLeft" X="-0.0226375348865986" Y="-0.181723222136497" Z="2.83468580245972" />
		<Joint Type="AnkleLeft" X="-0.0418602153658867" Y="-0.428377419710159" Z="2.82381439208984" />
		<Joint Type="FootLeft" X="-0.0450019612908363" Y="-0.473389804363251" Z="2.79035377502441" />
		<Joint Type="HipRight" X="0.0758783891797066" Y="0.148804396390915" Z="2.80906748771667" />
		<Joint Type="KneeRight" X="0.0591510124504566" Y="-0.175722703337669" Z="2.83023929595947" />
		<Joint Type="AnkleRight" X="0.0602934770286083" Y="-0.422339797019959" Z="2.81208753585815" />
		<Joint Type="FootRight" X="0.051274586468935" Y="-0.469384968280792" Z="2.77578568458557" />
	</BodyPosture>
	<BodyPosture Time="41108183.472" Joints="20">
		<Joint Type="HipCenter" X="0.0233345031738281" Y="0.200670197606087" Z="2.82038307189941" />
		<Joint Type="Spine" X="0.0173210967332125" Y="0.231693387031555" Z="2.86502432823181" />
		<Joint Type="ShoulderCenter" X="-7.61637929826975E-05" Y="0.454531788825989" Z="2.88627982139587" />
		<Joint Type="Head" X="0.0107404850423336" Y="0.582141518592834" Z="2.86928701400757" />
		<Joint Type="ShoulderLeft" X="-0.0968557894229889" Y="0.424802362918854" Z="2.89900898933411" />
		<Joint Type="ElbowLeft" X="-0.196383655071259" Y="0.618357062339783" Z="2.84486413002014" />
		<Joint Type="WristLeft" X="-0.231902778148651" Y="0.777272582054138" Z="2.83232498168945" />
		<Joint Type="HandLeft" X="-0.243464887142181" Y="0.831263542175293" Z="2.84580159187317" />
		<Joint Type="ShoulderRight" X="0.125665172934532" Y="0.438303649425507" Z="2.91813039779663" />
		<Joint Type="ElbowRight" X="0.205891191959381" Y="0.616292357444763" Z="2.87897253036499" />
		<Joint Type="WristRight" X="0.224822670221329" Y="0.777153730392456" Z="2.85193085670471" />
		<Joint Type="HandRight" X="0.232447251677513" Y="0.831953704357147" Z="2.86493682861328" />
		<Joint Type="HipLeft" X="-0.0211213175207376" Y="0.15095841884613" Z="2.80245423316956" />
		<Joint Type="KneeLeft" X="-0.0223468840122223" Y="-0.176643192768097" Z="2.8327009677887" />
		<Joint Type="AnkleLeft" X="-0.0385083332657814" Y="-0.427536606788635" Z="2.82283353805542" />
		<Joint Type="FootLeft" X="-0.03891421854496" Y="-0.47325798869133" Z="2.79160165786743" />
		<Joint Type="HipRight" X="0.0755171701312065" Y="0.155010342597961" Z="2.80933690071106" />
		<Joint Type="KneeRight" X="0.0649169310927391" Y="-0.168839991092682" Z="2.82666230201721" />
		<Joint Type="AnkleRight" X="0.0616203397512436" Y="-0.421570360660553" Z="2.81502103805542" />
		<Joint Type="FootRight" X="0.0523508042097092" Y="-0.4692023396492" Z="2.77966356277466" />
	</BodyPosture>
	<BodyPosture Time="41108308.2722" Joints="20">
		<Joint Type="HipCenter" X="0.0229170098900795" Y="0.204215839505196" Z="2.8213062286377" />
		<Joint Type="Spine" X="0.0185328014194965" Y="0.234523832798004" Z="2.86607718467712" />
		<Joint Type="ShoulderCenter" X="0.00173937890212983" Y="0.456065118312836" Z="2.88936328887939" />
		<Joint Type="Head" X="0.00992663111537695" Y="0.583790898323059" Z="2.86969494819641" />
		<Joint Type="ShoulderLeft" X="-0.0957622602581978" Y="0.428340315818787" Z="2.90833330154419" />
		<Joint Type="ElbowLeft" X="-0.192013934254646" Y="0.621955156326294" Z="2.846107006073" />
		<Joint Type="WristLeft" X="-0.23564712703228" Y="0.77882045507431" Z="2.83948588371277" />
		<Joint Type="HandLeft" X="-0.249098926782608" Y="0.832202196121216" Z="2.85366988182068" />
		<Joint Type="ShoulderRight" X="0.126314550638199" Y="0.448587596416473" Z="2.91980195045471" />
		<Joint Type="ElbowRight" X="0.20435756444931" Y="0.618401646614075" Z="2.88203072547913" />
		<Joint Type="WristRight" X="0.221217185258865" Y="0.779362976551056" Z="2.85376477241516" />
		<Joint Type="HandRight" X="0.227975144982338" Y="0.834396600723267" Z="2.86630964279175" />
		<Joint Type="HipLeft" X="-0.0216003265231848" Y="0.154284596443176" Z="2.8043212890625" />
		<Joint Type="KneeLeft" X="-0.0221774093806744" Y="-0.173801273107529" Z="2.83083748817444" />
		<Joint Type="AnkleLeft" X="-0.0401593931019306" Y="-0.426944196224213" Z="2.82180738449097" />
		<Joint Type="FootLeft" X="-0.0452534109354019" Y="-0.473645925521851" Z="2.79541420936584" />
		<Joint Type="HipRight" X="0.0746902674436569" Y="0.159088745713234" Z="2.80852723121643" />
		<Joint Type="KneeRight" X="0.0631125792860985" Y="-0.169365808367729" Z="2.82949185371399" />
		<Joint Type="AnkleRight" X="0.0631817057728767" Y="-0.421872138977051" Z="2.81349921226501" />
		<Joint Type="FootRight" X="0.0549774132668972" Y="-0.469004333019257" Z="2.78017830848694" />
	</BodyPosture>
	<BodyPosture Time="41108417.4724" Joints="20">
		<Joint Type="HipCenter" X="0.0231990292668343" Y="0.205753326416016" Z="2.82076215744019" />
		<Joint Type="Spine" X="0.0195786524564028" Y="0.236480519175529" Z="2.8653244972229" />
		<Joint Type="ShoulderCenter" X="0.00766780273988843" Y="0.455175131559372" Z="2.8845808506012" />
		<Joint Type="Head" X="0.00787065550684929" Y="0.583205103874207" Z="2.87052249908447" />
		<Joint Type="ShoulderLeft" X="-0.0961863398551941" Y="0.426045060157776" Z="2.90785932540894" />
		<Joint Type="ElbowLeft" X="-0.173721298575401" Y="0.568861484527588" Z="2.86393523216248" />
		<Joint Type="WristLeft" X="-0.221443474292755" Y="0.723965883255005" Z="2.84012842178345" />
		<Joint Type="HandLeft" X="-0.23491159081459" Y="0.777926385402679" Z="2.85199642181396" />
		<Joint Type="ShoulderRight" X="0.126424819231033" Y="0.448444068431854" Z="2.91884350776672" />
		<Joint Type="ElbowRight" X="0.203500956296921" Y="0.621234714984894" Z="2.88510489463806" />
		<Joint Type="WristRight" X="0.217001706361771" Y="0.783077001571655" Z="2.86286234855652" />
		<Joint Type="HandRight" X="0.221913978457451" Y="0.839139997959137" Z="2.87103486061096" />
		<Joint Type="HipLeft" X="-0.0213889461010695" Y="0.155289798974991" Z="2.80440211296082" />
		<Joint Type="KneeLeft" X="-0.0215559676289558" Y="-0.172867953777313" Z="2.83073329925537" />
		<Joint Type="AnkleLeft" X="-0.0395319163799286" Y="-0.428888559341431" Z="2.82027435302734" />
		<Joint Type="FootLeft" X="-0.0475982502102852" Y="-0.473061829805374" Z="2.79421091079712" />
		<Joint Type="HipRight" X="0.0742814615368843" Y="0.160323590040207" Z="2.8080141544342" />
		<Joint Type="KneeRight" X="0.0597071386873722" Y="-0.168066740036011" Z="2.828932762146" />
		<Joint Type="AnkleRight" X="0.0548678897321224" Y="-0.423718839883804" Z="2.81080937385559" />
		<Joint Type="FootRight" X="0.0546060167253017" Y="-0.469168215990067" Z="2.78087210655212" />
	</BodyPosture>
	<BodyPosture Time="41108557.8727" Joints="20">
		<Joint Type="HipCenter" X="0.0233787652105093" Y="0.206592246890068" Z="2.82085967063904" />
		<Joint Type="Spine" X="0.0196357294917107" Y="0.237049013376236" Z="2.86538982391357" />
		<Joint Type="ShoulderCenter" X="0.00756597332656384" Y="0.4550721347332" Z="2.88480663299561" />
		<Joint Type="Head" X="0.00466748420149088" Y="0.584225654602051" Z="2.87325191497803" />
		<Joint Type="ShoulderLeft" X="-0.0978322550654411" Y="0.423936009407043" Z="2.90691876411438" />
		<Joint Type="ElbowLeft" X="-0.180410921573639" Y="0.569550693035126" Z="2.85038137435913" />
		<Joint Type="WristLeft" X="-0.221973091363907" Y="0.726983368396759" Z="2.8431282043457" />
		<Joint Type="HandLeft" X="-0.236432582139969" Y="0.780517518520355" Z="2.85581159591675" />
		<Joint Type="ShoulderRight" X="0.126306220889091" Y="0.448726058006287" Z="2.91954684257507" />
		<Joint Type="ElbowRight" X="0.20364847779274" Y="0.621351778507233" Z="2.88566613197327" />
		<Joint Type="WristRight" X="0.215794414281845" Y="0.783329427242279" Z="2.86389136314392" />
		<Joint Type="HandRight" X="0.219281420111656" Y="0.83928245306015" Z="2.87353229522705" />
		<Joint Type="HipLeft" X="-0.021381963044405" Y="0.156286910176277" Z="2.80391955375671" />
		<Joint Type="KneeLeft" X="-0.019425243139267" Y="-0.171988472342491" Z="2.82950282096863" />
		<Joint Type="AnkleLeft" X="-0.037365548312664" Y="-0.427206009626389" Z="2.82191944122314" />
		<Joint Type="FootLeft" X="-0.0430381558835506" Y="-0.472520530223846" Z="2.7936806678772" />
		<Joint Type="HipRight" X="0.0747669860720634" Y="0.160639926791191" Z="2.80866408348084" />
		<Joint Type="KneeRight" X="0.0587728060781956" Y="-0.167729899287224" Z="2.82953643798828" />
		<Joint Type="AnkleRight" X="0.0609963908791542" Y="-0.424277871847153" Z="2.81183099746704" />
		<Joint Type="FootRight" X="0.0567082539200783" Y="-0.470206767320633" Z="2.78036713600159" />
	</BodyPosture>
	<BodyPosture Time="41108667.0729" Joints="20">
		<Joint Type="HipCenter" X="0.0232655722647905" Y="0.207691222429276" Z="2.82084441184998" />
		<Joint Type="Spine" X="0.0195650234818459" Y="0.237508460879326" Z="2.86536264419556" />
		<Joint Type="ShoulderCenter" X="0.00834903307259083" Y="0.45371425151825" Z="2.88679432868958" />
		<Joint Type="Head" X="0.00329250143840909" Y="0.585157155990601" Z="2.87679672241211" />
		<Joint Type="ShoulderLeft" X="-0.0994046702980995" Y="0.426462650299072" Z="2.90828895568848" />
		<Joint Type="ElbowLeft" X="-0.182371705770493" Y="0.566985964775085" Z="2.84961318969727" />
		<Joint Type="WristLeft" X="-0.221815422177315" Y="0.724953472614288" Z="2.84256410598755" />
		<Joint Type="HandLeft" X="-0.237445920705795" Y="0.778468608856201" Z="2.85397982597351" />
		<Joint Type="ShoulderRight" X="0.125863954424858" Y="0.447440266609192" Z="2.92111897468567" />
		<Joint Type="ElbowRight" X="0.203973025083542" Y="0.618813037872314" Z="2.88314294815063" />
		<Joint Type="WristRight" X="0.216532766819" Y="0.781064212322235" Z="2.86707258224487" />
		<Joint Type="HandRight" X="0.218597754836082" Y="0.837037920951843" Z="2.87713146209717" />
		<Joint Type="HipLeft" X="-0.0220475196838379" Y="0.157450988888741" Z="2.80293798446655" />
		<Joint Type="KneeLeft" X="-0.020493570715189" Y="-0.170615419745445" Z="2.83085942268372" />
		<Joint Type="AnkleLeft" X="-0.0379475243389606" Y="-0.427393794059753" Z="2.82548213005066" />
		<Joint Type="FootLeft" X="-0.0382959693670273" Y="-0.473770767450333" Z="2.79606032371521" />
		<Joint Type="HipRight" X="0.0748225674033165" Y="0.161015495657921" Z="2.8090398311615" />
		<Joint Type="KneeRight" X="0.0642871633172035" Y="-0.167711839079857" Z="2.82898902893066" />
		<Joint Type="AnkleRight" X="0.0584123022854328" Y="-0.423970997333527" Z="2.81384444236755" />
		<Joint Type="FootRight" X="0.0571183823049068" Y="-0.470663517713547" Z="2.78290462493896" />
	</BodyPosture>
	<BodyPosture Time="41108791.8731" Joints="20">
		<Joint Type="HipCenter" X="0.0238825287669897" Y="0.206130102276802" Z="2.82091331481934" />
		<Joint Type="Spine" X="0.0192342363297939" Y="0.23606064915657" Z="2.86536884307861" />
		<Joint Type="ShoulderCenter" X="0.00730384700000286" Y="0.452703386545181" Z="2.88700890541077" />
		<Joint Type="Head" X="0.00309458840638399" Y="0.585277080535889" Z="2.87768721580505" />
		<Joint Type="ShoulderLeft" X="-0.0988191962242126" Y="0.410173237323761" Z="2.8976411819458" />
		<Joint Type="ElbowLeft" X="-0.187659204006195" Y="0.563795447349548" Z="2.84604907035828" />
		<Joint Type="WristLeft" X="-0.225758880376816" Y="0.722050845623016" Z="2.83145260810852" />
		<Joint Type="HandLeft" X="-0.240071892738342" Y="0.77676796913147" Z="2.83796048164368" />
		<Joint Type="ShoulderRight" X="0.126983031630516" Y="0.44797083735466" Z="2.92112135887146" />
		<Joint Type="ElbowRight" X="0.205823078751564" Y="0.616516828536987" Z="2.87973523139954" />
		<Joint Type="WristRight" X="0.216359794139862" Y="0.778541147708893" Z="2.85723972320557" />
		<Joint Type="HandRight" X="0.217463731765747" Y="0.833567559719086" Z="2.87180185317993" />
		<Joint Type="HipLeft" X="-0.0208543948829174" Y="0.153954356908798" Z="2.80297327041626" />
		<Joint Type="KneeLeft" X="-0.0196808706969023" Y="-0.174065589904785" Z="2.83173441886902" />
		<Joint Type="AnkleLeft" X="-0.0313565619289875" Y="-0.43063086271286" Z="2.82755470275879" />
		<Joint Type="FootLeft" X="-0.0448163710534573" Y="-0.473875552415848" Z="2.79503226280212" />
		<Joint Type="HipRight" X="0.0755886659026146" Y="0.159473463892937" Z="2.80906105041504" />
		<Joint Type="KneeRight" X="0.0596090815961361" Y="-0.168998494744301" Z="2.82993626594543" />
		<Joint Type="AnkleRight" X="0.0516791120171547" Y="-0.42867112159729" Z="2.80890583992004" />
		<Joint Type="FootRight" X="0.0557584725320339" Y="-0.469769150018692" Z="2.78315925598145" />
	</BodyPosture>
	<BodyPosture Time="41108947.8734" Joints="20">
		<Joint Type="HipCenter" X="0.0235600173473358" Y="0.20025622844696" Z="2.82075357437134" />
		<Joint Type="Spine" X="0.0189607236534357" Y="0.231930509209633" Z="2.86550402641296" />
		<Joint Type="ShoulderCenter" X="0.00767720211297274" Y="0.452299773693085" Z="2.88755249977112" />
		<Joint Type="Head" X="0.00258844438940287" Y="0.58491039276123" Z="2.87777733802795" />
		<Joint Type="ShoulderLeft" X="-0.101771354675293" Y="0.402852416038513" Z="2.89570307731628" />
		<Joint Type="ElbowLeft" X="-0.194786787033081" Y="0.554146409034729" Z="2.83979249000549" />
		<Joint Type="WristLeft" X="-0.235439330339432" Y="0.707292497158051" Z="2.79215598106384" />
		<Joint Type="HandLeft" X="-0.246128529310226" Y="0.743897318840027" Z="2.79979276657104" />
		<Joint Type="ShoulderRight" X="0.129932940006256" Y="0.435624897480011" Z="2.91829586029053" />
		<Joint Type="ElbowRight" X="0.209420174360275" Y="0.610120058059692" Z="2.85509276390076" />
		<Joint Type="WristRight" X="0.222727224230766" Y="0.772316992282867" Z="2.83946418762207" />
		<Joint Type="HandRight" X="0.224210575222969" Y="0.828452706336975" Z="2.8489351272583" />
		<Joint Type="HipLeft" X="-0.0220181830227375" Y="0.146126747131348" Z="2.8009991645813" />
		<Joint Type="KneeLeft" X="-0.0205293670296669" Y="-0.181421637535095" Z="2.83375644683838" />
		<Joint Type="AnkleLeft" X="-0.0387418791651726" Y="-0.42917799949646" Z="2.82195091247559" />
		<Joint Type="FootLeft" X="-0.0445546694099903" Y="-0.473109096288681" Z="2.79354310035706" />
		<Joint Type="HipRight" X="0.0759567767381668" Y="0.15096840262413" Z="2.80961298942566" />
		<Joint Type="KneeRight" X="0.0609318614006042" Y="-0.177438259124756" Z="2.8319194316864" />
		<Joint Type="AnkleRight" X="0.056822195649147" Y="-0.421379417181015" Z="2.81367111206055" />
		<Joint Type="FootRight" X="0.0563449896872044" Y="-0.469467371702194" Z="2.7824399471283" />
	</BodyPosture>
	<BodyPosture Time="41109072.6736" Joints="20">
		<Joint Type="HipCenter" X="0.02152294293046" Y="0.180443450808525" Z="2.81921648979187" />
		<Joint Type="Spine" X="0.018216036260128" Y="0.2156021296978" Z="2.86541509628296" />
		<Joint Type="ShoulderCenter" X="0.00957233086228371" Y="0.451397329568863" Z="2.89271211624146" />
		<Joint Type="Head" X="0.00432306900620461" Y="0.584812819957733" Z="2.87820482254028" />
		<Joint Type="ShoulderLeft" X="-0.10399329662323" Y="0.39855831861496" Z="2.89435291290283" />
		<Joint Type="ElbowLeft" X="-0.210752338171005" Y="0.518220186233521" Z="2.79450678825378" />
		<Joint Type="WristLeft" X="-0.258742719888687" Y="0.664647459983826" Z="2.73178100585938" />
		<Joint Type="HandLeft" X="-0.264876931905746" Y="0.687800049781799" Z="2.74007678031921" />
		<Joint Type="ShoulderRight" X="0.126595020294189" Y="0.416883736848831" Z="2.90972328186035" />
		<Joint Type="ElbowRight" X="0.221131265163422" Y="0.552892625331879" Z="2.83806300163269" />
		<Joint Type="WristRight" X="0.23315118253231" Y="0.714379072189331" Z="2.81089401245117" />
		<Joint Type="HandRight" X="0.240147098898888" Y="0.770897746086121" Z="2.81228280067444" />
		<Joint Type="HipLeft" X="-0.0259644892066717" Y="0.127796053886414" Z="2.79936361312866" />
		<Joint Type="KneeLeft" X="-0.0223289951682091" Y="-0.190104007720947" Z="2.83716773986816" />
		<Joint Type="AnkleLeft" X="-0.0375498533248901" Y="-0.429083526134491" Z="2.82130599021912" />
		<Joint Type="FootLeft" X="-0.0421755835413933" Y="-0.474094331264496" Z="2.78910422325134" />
		<Joint Type="HipRight" X="0.0729707926511765" Y="0.13209043443203" Z="2.80729579925537" />
		<Joint Type="KneeRight" X="0.0594096630811691" Y="-0.188798785209656" Z="2.83413004875183" />
		<Joint Type="AnkleRight" X="0.0539261996746063" Y="-0.423191130161285" Z="2.8137218952179" />
		<Joint Type="FootRight" X="0.0583052225410938" Y="-0.469270527362823" Z="2.78355741500854" />
	</BodyPosture>
	<BodyPosture Time="41109228.6739" Joints="20">
		<Joint Type="HipCenter" X="0.0199627280235291" Y="0.153285950422287" Z="2.81655812263489" />
		<Joint Type="Spine" X="0.0167836621403694" Y="0.191419795155525" Z="2.86458158493042" />
		<Joint Type="ShoulderCenter" X="0.0120990928262472" Y="0.446975469589233" Z="2.9017481803894" />
		<Joint Type="Head" X="0.00437265960499644" Y="0.584141075611115" Z="2.88266015052795" />
		<Joint Type="ShoulderLeft" X="-0.0990922749042511" Y="0.365450382232666" Z="2.89023518562317" />
		<Joint Type="ElbowLeft" X="-0.228020310401917" Y="0.376479119062424" Z="2.76000142097473" />
		<Joint Type="WristLeft" X="-0.284872502088547" Y="0.473829001188278" Z="2.63244962692261" />
		<Joint Type="HandLeft" X="-0.269093930721283" Y="0.508027374744415" Z="2.63876843452454" />
		<Joint Type="ShoulderRight" X="0.127657935023308" Y="0.394331336021423" Z="2.91200304031372" />
		<Joint Type="ElbowRight" X="0.256097584962845" Y="0.450415253639221" Z="2.80934166908264" />
		<Joint Type="WristRight" X="0.245347961783409" Y="0.597989976406097" Z="2.7313404083252" />
		<Joint Type="HandRight" X="0.246547386050224" Y="0.629301428794861" Z="2.74079847335815" />
		<Joint Type="HipLeft" X="-0.0274086110293865" Y="0.103877522051334" Z="2.79488015174866" />
		<Joint Type="KneeLeft" X="-0.0236884355545044" Y="-0.197980120778084" Z="2.84217381477356" />
		<Joint Type="AnkleLeft" X="-0.0391257330775261" Y="-0.430018693208694" Z="2.82007050514221" />
		<Joint Type="FootLeft" X="-0.0480308681726456" Y="-0.473741203546524" Z="2.79266285896301" />
		<Joint Type="HipRight" X="0.0701523572206497" Y="0.105719074606895" Z="2.80575203895569" />
		<Joint Type="KneeRight" X="0.0545471906661987" Y="-0.192960932850838" Z="2.83718967437744" />
		<Joint Type="AnkleRight" X="0.0520931556820869" Y="-0.42359322309494" Z="2.81426858901978" />
		<Joint Type="FootRight" X="0.0586397312581539" Y="-0.469522833824158" Z="2.78380727767944" />
	</BodyPosture>
	<BodyPosture Time="41109322.274" Joints="20">
		<Joint Type="HipCenter" X="0.0199859421700239" Y="0.1454037129879" Z="2.81861257553101" />
		<Joint Type="Spine" X="0.0146323852241039" Y="0.184091344475746" Z="2.86663794517517" />
		<Joint Type="ShoulderCenter" X="0.0126479119062424" Y="0.445050895214081" Z="2.90807104110718" />
		<Joint Type="Head" X="0.00710718333721161" Y="0.583162307739258" Z="2.88317942619324" />
		<Joint Type="ShoulderLeft" X="-0.0976711139082909" Y="0.354140162467957" Z="2.88619661331177" />
		<Joint Type="ElbowLeft" X="-0.210291430354118" Y="0.275439292192459" Z="2.77910900115967" />
		<Joint Type="WristLeft" X="-0.252431124448776" Y="0.21970497071743" Z="2.6220064163208" />
		<Joint Type="HandLeft" X="-0.258677899837494" Y="0.227467909455299" Z="2.6203601360321" />
		<Joint Type="ShoulderRight" X="0.128612905740738" Y="0.373168349266052" Z="2.9194667339325" />
		<Joint Type="ElbowRight" X="0.253173023462296" Y="0.320442289113998" Z="2.80910658836365" />
		<Joint Type="WristRight" X="0.260503023862839" Y="0.422268182039261" Z="2.67224025726318" />
		<Joint Type="HandRight" X="0.26457491517067" Y="0.426145702600479" Z="2.6664674282074" />
		<Joint Type="HipLeft" X="-0.0276702381670475" Y="0.0957983732223511" Z="2.79512500762939" />
		<Joint Type="KneeLeft" X="-0.0249273087829351" Y="-0.201157361268997" Z="2.84275007247925" />
		<Joint Type="AnkleLeft" X="-0.0396919026970863" Y="-0.427750617265701" Z="2.82338976860046" />
		<Joint Type="FootLeft" X="-0.0492142289876938" Y="-0.473782986402512" Z="2.79073309898376" />
		<Joint Type="HipRight" X="0.0700581893324852" Y="0.0957074463367462" Z="2.8100700378418" />
		<Joint Type="KneeRight" X="0.0497013442218304" Y="-0.199553027749062" Z="2.83849263191223" />
		<Joint Type="AnkleRight" X="0.0548360459506512" Y="-0.424482882022858" Z="2.81415796279907" />
		<Joint Type="FootRight" X="0.0587573535740376" Y="-0.470030397176743" Z="2.78328251838684" />
	</BodyPosture>
	<BodyPosture Time="41109462.6743" Joints="20">
		<Joint Type="HipCenter" X="0.01926564052701" Y="0.140640303492546" Z="2.81985855102539" />
		<Joint Type="Spine" X="0.0134937353432178" Y="0.180355846881866" Z="2.86803245544434" />
		<Joint Type="ShoulderCenter" X="0.0124306092038751" Y="0.445301413536072" Z="2.91019654273987" />
		<Joint Type="Head" X="0.00657938420772552" Y="0.58660888671875" Z="2.88627338409424" />
		<Joint Type="ShoulderLeft" X="-0.103399850428104" Y="0.348154813051224" Z="2.88101816177368" />
		<Joint Type="ElbowLeft" X="-0.177773416042328" Y="0.224999517202377" Z="2.78513669967651" />
		<Joint Type="WristLeft" X="-0.203325837850571" Y="0.101689428091049" Z="2.67195892333984" />
		<Joint Type="HandLeft" X="-0.211533173918724" Y="0.0537946857511997" Z="2.61729860305786" />
		<Joint Type="ShoulderRight" X="0.124041013419628" Y="0.366997510194778" Z="2.91758561134338" />
		<Joint Type="ElbowRight" X="0.212880343198776" Y="0.252115815877914" Z="2.82432317733765" />
		<Joint Type="WristRight" X="0.273716449737549" Y="0.267747193574905" Z="2.66409730911255" />
		<Joint Type="HandRight" X="0.269470989704132" Y="0.258562058210373" Z="2.65534496307373" />
		<Joint Type="HipLeft" X="-0.0290809087455273" Y="0.0896078050136566" Z="2.79517197608948" />
		<Joint Type="KneeLeft" X="-0.0260696783661842" Y="-0.200975492596626" Z="2.8418276309967" />
		<Joint Type="AnkleLeft" X="-0.0407025925815105" Y="-0.427341461181641" Z="2.82474207878113" />
		<Joint Type="FootLeft" X="-0.0488578528165817" Y="-0.474295496940613" Z="2.7943549156189" />
		<Joint Type="HipRight" X="0.0698269307613373" Y="0.0913365259766579" Z="2.81201791763306" />
		<Joint Type="KneeRight" X="0.0498575828969479" Y="-0.20040737092495" Z="2.83862805366516" />
		<Joint Type="AnkleRight" X="0.0572231486439705" Y="-0.421268314123154" Z="2.81438517570496" />
		<Joint Type="FootRight" X="0.0586988590657711" Y="-0.470186918973923" Z="2.78284931182861" />
	</BodyPosture>
	<BodyPosture Time="41109571.8745" Joints="20">
		<Joint Type="HipCenter" X="0.0176910758018494" Y="0.13585501909256" Z="2.82083797454834" />
		<Joint Type="Spine" X="0.0119668915867805" Y="0.177031949162483" Z="2.86886358261108" />
		<Joint Type="ShoulderCenter" X="0.0113322669640183" Y="0.446443319320679" Z="2.90869665145874" />
		<Joint Type="Head" X="0.00597335211932659" Y="0.589912116527557" Z="2.88814735412598" />
		<Joint Type="ShoulderLeft" X="-0.104418225586414" Y="0.344462305307388" Z="2.87631225585938" />
		<Joint Type="ElbowLeft" X="-0.139847964048386" Y="0.153663158416748" Z="2.78839373588562" />
		<Joint Type="WristLeft" X="-0.143625423312187" Y="-0.00438730418682098" Z="2.73978972434998" />
		<Joint Type="HandLeft" X="-0.142684400081635" Y="-0.0352569185197353" Z="2.73576211929321" />
		<Joint Type="ShoulderRight" X="0.122313760221004" Y="0.359306812286377" Z="2.91157841682434" />
		<Joint Type="ElbowRight" X="0.213803082704544" Y="0.227747201919556" Z="2.86349511146545" />
		<Joint Type="WristRight" X="0.229635313153267" Y="0.116963274776936" Z="2.73527336120605" />
		<Joint Type="HandRight" X="0.23204080760479" Y="0.0859848111867905" Z="2.69763326644897" />
		<Joint Type="HipLeft" X="-0.0309828147292137" Y="0.0854520201683044" Z="2.79545378684998" />
		<Joint Type="KneeLeft" X="-0.027959018945694" Y="-0.20347061753273" Z="2.83987092971802" />
		<Joint Type="AnkleLeft" X="-0.045428529381752" Y="-0.427207827568054" Z="2.8242039680481" />
		<Joint Type="FootLeft" X="-0.0499357134103775" Y="-0.473832011222839" Z="2.79370045661926" />
		<Joint Type="HipRight" X="0.068264402449131" Y="0.0855948925018311" Z="2.81482124328613" />
		<Joint Type="KneeRight" X="0.0519077628850937" Y="-0.202059060335159" Z="2.83849287033081" />
		<Joint Type="AnkleRight" X="0.0602985993027687" Y="-0.419709444046021" Z="2.81451559066772" />
		<Joint Type="FootRight" X="0.0586245246231556" Y="-0.470227271318436" Z="2.78317427635193" />
	</BodyPosture>
	<BodyPosture Time="41109727.8747" Joints="20">
		<Joint Type="HipCenter" X="0.0216737687587738" Y="0.134950444102287" Z="2.82234883308411" />
		<Joint Type="Spine" X="0.0141948815435171" Y="0.177021145820618" Z="2.86944222450256" />
		<Joint Type="ShoulderCenter" X="0.0100543210282922" Y="0.448251396417618" Z="2.90430307388306" />
		<Joint Type="Head" X="0.00563429715111852" Y="0.590013742446899" Z="2.88594675064087" />
		<Joint Type="ShoulderLeft" X="-0.104630067944527" Y="0.344787955284119" Z="2.87501311302185" />
		<Joint Type="ElbowLeft" X="-0.123592644929886" Y="0.15046726167202" Z="2.82066679000854" />
		<Joint Type="WristLeft" X="-0.124671712517738" Y="-0.00483037531375885" Z="2.7620325088501" />
		<Joint Type="HandLeft" X="-0.120853438973427" Y="-0.0367913618683815" Z="2.76597785949707" />
		<Joint Type="ShoulderRight" X="0.122304774820805" Y="0.357601046562195" Z="2.91179418563843" />
		<Joint Type="ElbowRight" X="0.183644816279411" Y="0.169493272900581" Z="2.87265467643738" />
		<Joint Type="WristRight" X="0.191224634647369" Y="0.0195881575345993" Z="2.79974484443665" />
		<Joint Type="HandRight" X="0.213789001107216" Y="-0.0200275536626577" Z="2.80680656433105" />
		<Joint Type="HipLeft" X="-0.0258884746581316" Y="0.0842698663473129" Z="2.79766917228699" />
		<Joint Type="KneeLeft" X="-0.0271958969533443" Y="-0.203562080860138" Z="2.83792948722839" />
		<Joint Type="AnkleLeft" X="-0.0463328026235104" Y="-0.427524507045746" Z="2.82154703140259" />
		<Joint Type="FootLeft" X="-0.0418901741504669" Y="-0.473418235778809" Z="2.79078388214111" />
		<Joint Type="HipRight" X="0.0742513462901115" Y="0.0843375697731972" Z="2.81843614578247" />
		<Joint Type="KneeRight" X="0.0525885336101055" Y="-0.20085221529007" Z="2.8381655216217" />
		<Joint Type="AnkleRight" X="0.0546082891523838" Y="-0.419672429561615" Z="2.81423330307007" />
		<Joint Type="FootRight" X="0.0596408918499947" Y="-0.470374464988709" Z="2.78314852714539" />
	</BodyPosture>
</BodyGesture>
