<BodyGesture Name="slice carrots" Postures="21">
	<BodyPosture Time="35220904.4409" Joints="20">
		<Joint Type="HipCenter" X="0.0422350838780403" Y="0.214148059487343" Z="2.53786420822144" />
		<Joint Type="Spine" X="0.0427617803215981" Y="0.25671860575676" Z="2.54617214202881" />
		<Joint Type="ShoulderCenter" X="0.0463357046246529" Y="0.474912822246552" Z="2.53438854217529" />
		<Joint Type="Head" X="0.0569753125309944" Y="0.610533595085144" Z="2.457848072052" />
		<Joint Type="ShoulderLeft" X="-0.0873484238982201" Y="0.410007536411285" Z="2.5531747341156" />
		<Joint Type="ElbowLeft" X="-0.142930686473846" Y="0.222222208976746" Z="2.56227898597717" />
		<Joint Type="WristLeft" X="-0.160620540380478" Y="0.0734085142612457" Z="2.51063179969788" />
		<Joint Type="HandLeft" X="-0.17594188451767" Y="0.0304465480148792" Z="2.51038002967834" />
		<Joint Type="ShoulderRight" X="0.17141717672348" Y="0.389490246772766" Z="2.55452227592468" />
		<Joint Type="ElbowRight" X="0.189813405275345" Y="0.208362460136414" Z="2.58186626434326" />
		<Joint Type="WristRight" X="0.180266320705414" Y="0.0580185204744339" Z="2.53315687179565" />
		<Joint Type="HandRight" X="0.181822702288628" Y="-0.00255386903882027" Z="2.52145719528198" />
		<Joint Type="HipLeft" X="-0.0180194694548845" Y="0.153465270996094" Z="2.52670979499817" />
		<Joint Type="KneeLeft" X="-0.00145911611616611" Y="-0.172650516033173" Z="2.54879570007324" />
		<Joint Type="AnkleLeft" X="-0.0195366106927395" Y="-0.376938164234161" Z="2.526939868927" />
		<Joint Type="FootLeft" X="-0.00658032856881619" Y="-0.416592836380005" Z="2.47357416152954" />
		<Joint Type="HipRight" X="0.101651638746262" Y="0.156905308365822" Z="2.54971408843994" />
		<Joint Type="KneeRight" X="0.0258961841464043" Y="-0.14125283062458" Z="2.55014443397522" />
		<Joint Type="AnkleRight" X="0.0229970533400774" Y="-0.375492751598358" Z="2.51589608192444" />
		<Joint Type="FootRight" X="0.00225164764560759" Y="-0.412932991981506" Z="2.4743332862854" />
	</BodyPosture>
	<BodyPosture Time="35221032.4482" Joints="20">
		<Joint Type="HipCenter" X="0.0393662713468075" Y="0.217323422431946" Z="2.53879523277283" />
		<Joint Type="Spine" X="0.0401737987995148" Y="0.260719537734985" Z="2.54877543449402" />
		<Joint Type="ShoulderCenter" X="0.0418245978653431" Y="0.485547184944153" Z="2.54506993293762" />
		<Joint Type="Head" X="0.0446470901370049" Y="0.631542921066284" Z="2.485107421875" />
		<Joint Type="ShoulderLeft" X="-0.0915946289896965" Y="0.41066563129425" Z="2.55929970741272" />
		<Joint Type="ElbowLeft" X="-0.142127305269241" Y="0.221354946494102" Z="2.57217121124268" />
		<Joint Type="WristLeft" X="-0.156388968229294" Y="0.0724442154169083" Z="2.51954483985901" />
		<Joint Type="HandLeft" X="-0.17105421423912" Y="0.0299028269946575" Z="2.51208448410034" />
		<Joint Type="ShoulderRight" X="0.164536878466606" Y="0.396398901939392" Z="2.55082392692566" />
		<Joint Type="ElbowRight" X="0.187872007489204" Y="0.207951918244362" Z="2.57129383087158" />
		<Joint Type="WristRight" X="0.182508111000061" Y="0.0572643429040909" Z="2.52309465408325" />
		<Joint Type="HandRight" X="0.184688821434975" Y="-0.00375375151634216" Z="2.51413488388062" />
		<Joint Type="HipLeft" X="-0.0208716280758381" Y="0.159398078918457" Z="2.52750968933105" />
		<Joint Type="KneeLeft" X="0.00681386888027191" Y="-0.169640347361565" Z="2.5522825717926" />
		<Joint Type="AnkleLeft" X="-0.00799841806292534" Y="-0.378209471702576" Z="2.53635191917419" />
		<Joint Type="FootLeft" X="0.000978294294327497" Y="-0.418514519929886" Z="2.48109936714172" />
		<Joint Type="HipRight" X="0.0970117747783661" Y="0.159306675195694" Z="2.54621529579163" />
		<Joint Type="KneeRight" X="0.0274509321898222" Y="-0.135344386100769" Z="2.55072951316834" />
		<Joint Type="AnkleRight" X="0.0298837572336197" Y="-0.37493172287941" Z="2.52322840690613" />
		<Joint Type="FootRight" X="0.00685553345829248" Y="-0.415082693099976" Z="2.48059821128845" />
	</BodyPosture>
	<BodyPosture Time="35221133.454" Joints="20">
		<Joint Type="HipCenter" X="0.0297915861010551" Y="0.219157874584198" Z="2.53997921943665" />
		<Joint Type="Spine" X="0.0310739986598492" Y="0.262907028198242" Z="2.55478119850159" />
		<Joint Type="ShoulderCenter" X="0.0322724394500256" Y="0.493324786424637" Z="2.55769777297974" />
		<Joint Type="Head" X="0.0262407101690769" Y="0.637796938419342" Z="2.51291441917419" />
		<Joint Type="ShoulderLeft" X="-0.101656787097454" Y="0.406560599803925" Z="2.56907057762146" />
		<Joint Type="ElbowLeft" X="-0.145735532045364" Y="0.212228253483772" Z="2.57999348640442" />
		<Joint Type="WristLeft" X="-0.156026527285576" Y="0.0623079389333725" Z="2.52981352806091" />
		<Joint Type="HandLeft" X="-0.164397791028023" Y="0.0184415839612484" Z="2.52052998542786" />
		<Joint Type="ShoulderRight" X="0.155953481793404" Y="0.401259422302246" Z="2.55557799339294" />
		<Joint Type="ElbowRight" X="0.185194328427315" Y="0.20912379026413" Z="2.57109403610229" />
		<Joint Type="WristRight" X="0.178270861506462" Y="0.0607967078685761" Z="2.51475048065186" />
		<Joint Type="HandRight" X="0.178315535187721" Y="0.000426050275564194" Z="2.50195717811584" />
		<Joint Type="HipLeft" X="-0.0311130732297897" Y="0.163558959960938" Z="2.52697205543518" />
		<Joint Type="KneeLeft" X="0.008668745867908" Y="-0.172002181410789" Z="2.55224061012268" />
		<Joint Type="AnkleLeft" X="-0.00658807810395956" Y="-0.380736351013184" Z="2.53581571578979" />
		<Joint Type="FootLeft" X="0.00479980045929551" Y="-0.420942038297653" Z="2.479168176651" />
		<Joint Type="HipRight" X="0.0878002941608429" Y="0.159065276384354" Z="2.5435676574707" />
		<Joint Type="KneeRight" X="0.0307960193604231" Y="-0.134159699082375" Z="2.5502188205719" />
		<Joint Type="AnkleRight" X="0.0301610622555017" Y="-0.375658512115479" Z="2.52402138710022" />
		<Joint Type="FootRight" X="0.00743443146348" Y="-0.416482537984848" Z="2.48095774650574" />
	</BodyPosture>
	<BodyPosture Time="35221378.4593" Joints="20">
		<Joint Type="HipCenter" X="0.0234132613986731" Y="0.22029222548008" Z="2.5432391166687" />
		<Joint Type="Spine" X="0.0228956118226051" Y="0.26362681388855" Z="2.56601476669312" />
		<Joint Type="ShoulderCenter" X="0.0191929806023836" Y="0.499499917030334" Z="2.57287001609802" />
		<Joint Type="Head" X="0.0168459061533213" Y="0.641858577728271" Z="2.52562141418457" />
		<Joint Type="ShoulderLeft" X="-0.110682383179665" Y="0.404012948274612" Z="2.57454824447632" />
		<Joint Type="ElbowLeft" X="-0.147860005497932" Y="0.210134521126747" Z="2.58133602142334" />
		<Joint Type="WristLeft" X="-0.155612990260124" Y="0.0588963627815247" Z="2.53575849533081" />
		<Joint Type="HandLeft" X="-0.156624585390091" Y="0.0308467447757721" Z="2.53859043121338" />
		<Joint Type="ShoulderRight" X="0.145628213882446" Y="0.404839307069778" Z="2.57398152351379" />
		<Joint Type="ElbowRight" X="0.173067405819893" Y="0.204958230257034" Z="2.57579374313354" />
		<Joint Type="WristRight" X="0.173179507255554" Y="0.060049295425415" Z="2.50921869277954" />
		<Joint Type="HandRight" X="0.176362350583076" Y="0.000705186277627945" Z="2.52585768699646" />
		<Joint Type="HipLeft" X="-0.0361130759119987" Y="0.165152430534363" Z="2.52778196334839" />
		<Joint Type="KneeLeft" X="0.0120082311332226" Y="-0.171487599611282" Z="2.54760360717773" />
		<Joint Type="AnkleLeft" X="-0.00693778181448579" Y="-0.383136749267578" Z="2.53350067138672" />
		<Joint Type="FootLeft" X="0.007222187705338" Y="-0.421038240194321" Z="2.47999596595764" />
		<Joint Type="HipRight" X="0.0829420536756516" Y="0.158638432621956" Z="2.5450496673584" />
		<Joint Type="KneeRight" X="0.0326419062912464" Y="-0.127518087625504" Z="2.54170346260071" />
		<Joint Type="AnkleRight" X="0.0292614493519068" Y="-0.375243902206421" Z="2.52100253105164" />
		<Joint Type="FootRight" X="0.00750808278098702" Y="-0.416959941387177" Z="2.4804048538208" />
	</BodyPosture>
	<BodyPosture Time="35221518.8596" Joints="20">
		<Joint Type="HipCenter" X="0.0191629137843847" Y="0.216081321239471" Z="2.54942035675049" />
		<Joint Type="Spine" X="0.0152562176808715" Y="0.259745091199875" Z="2.58007621765137" />
		<Joint Type="ShoulderCenter" X="0.0118603771552444" Y="0.501165568828583" Z="2.57924771308899" />
		<Joint Type="Head" X="0.00862327683717012" Y="0.646214485168457" Z="2.54414558410645" />
		<Joint Type="ShoulderLeft" X="-0.115879416465759" Y="0.398079484701157" Z="2.56567692756653" />
		<Joint Type="ElbowLeft" X="-0.147698134183884" Y="0.207184225320816" Z="2.56204271316528" />
		<Joint Type="WristLeft" X="-0.151085436344147" Y="0.0593131184577942" Z="2.50382947921753" />
		<Joint Type="HandLeft" X="-0.151024714112282" Y="0.0249509997665882" Z="2.49809527397156" />
		<Joint Type="ShoulderRight" X="0.140296161174774" Y="0.410637527704239" Z="2.59199571609497" />
		<Joint Type="ElbowRight" X="0.173172533512115" Y="0.260067105293274" Z="2.59352159500122" />
		<Joint Type="WristRight" X="0.186029881238937" Y="0.216917008161545" Z="2.3955135345459" />
		<Joint Type="HandRight" X="0.185353383421898" Y="0.201584905385971" Z="2.38133454322815" />
		<Joint Type="HipLeft" X="-0.0371466502547264" Y="0.15828350186348" Z="2.52939748764038" />
		<Joint Type="KneeLeft" X="-0.0063156932592392" Y="-0.149507194757462" Z="2.53661417961121" />
		<Joint Type="AnkleLeft" X="-0.00986152142286301" Y="-0.369576871395111" Z="2.55094218254089" />
		<Joint Type="FootLeft" X="-0.0256182532757521" Y="-0.415739446878433" Z="2.5295684337616" />
		<Joint Type="HipRight" X="0.0783777832984924" Y="0.155129432678223" Z="2.55389547348022" />
		<Joint Type="KneeRight" X="0.0507089756429195" Y="-0.144114285707474" Z="2.51751899719238" />
		<Joint Type="AnkleRight" X="0.0826007947325706" Y="-0.370715111494064" Z="2.49867224693298" />
		<Joint Type="FootRight" X="0.0827485248446465" Y="-0.414625346660614" Z="2.46241974830627" />
	</BodyPosture>
	<BodyPosture Time="35221643.6598" Joints="20">
		<Joint Type="HipCenter" X="0.0266437157988548" Y="0.211553439497948" Z="2.54520153999329" />
		<Joint Type="Spine" X="0.0277304947376251" Y="0.256716281175613" Z="2.57808303833008" />
		<Joint Type="ShoulderCenter" X="0.0244848839938641" Y="0.507230937480927" Z="2.5763795375824" />
		<Joint Type="Head" X="0.0143834240734577" Y="0.650091469287872" Z="2.5468590259552" />
		<Joint Type="ShoulderLeft" X="-0.108604572713375" Y="0.402226388454437" Z="2.56110310554504" />
		<Joint Type="ElbowLeft" X="-0.139475494623184" Y="0.210939824581146" Z="2.54415583610535" />
		<Joint Type="WristLeft" X="-0.143894210457802" Y="0.0622453391551971" Z="2.48865461349487" />
		<Joint Type="HandLeft" X="-0.14715588092804" Y="0.0324215032160282" Z="2.46708059310913" />
		<Joint Type="ShoulderRight" X="0.151069402694702" Y="0.404026597738266" Z="2.54381036758423" />
		<Joint Type="ElbowRight" X="0.205201223492622" Y="0.276828914880753" Z="2.45281910896301" />
		<Joint Type="WristRight" X="0.206110432744026" Y="0.371807634830475" Z="2.31961250305176" />
		<Joint Type="HandRight" X="0.204888015985489" Y="0.402409493923187" Z="2.26601481437683" />
		<Joint Type="HipLeft" X="-0.0318756029009819" Y="0.155782625079155" Z="2.52893686294556" />
		<Joint Type="KneeLeft" X="-0.000817355932667851" Y="-0.143557190895081" Z="2.53699278831482" />
		<Joint Type="AnkleLeft" X="-0.00461169378831983" Y="-0.369107872247696" Z="2.5487048625946" />
		<Joint Type="FootLeft" X="-0.0127991531044245" Y="-0.415327876806259" Z="2.52355813980103" />
		<Joint Type="HipRight" X="0.0862560719251633" Y="0.151252865791321" Z="2.54462242126465" />
		<Joint Type="KneeRight" X="0.0755630657076836" Y="-0.16554993391037" Z="2.53208637237549" />
		<Joint Type="AnkleRight" X="0.0793748125433922" Y="-0.370242416858673" Z="2.5074474811554" />
		<Joint Type="FootRight" X="0.0837278217077255" Y="-0.415953874588013" Z="2.47430729866028" />
	</BodyPosture>
	<BodyPosture Time="35221752.86" Joints="20">
		<Joint Type="HipCenter" X="0.0439502447843552" Y="0.206549346446991" Z="2.51856970787048" />
		<Joint Type="Spine" X="0.0489074774086475" Y="0.250938475131989" Z="2.55489444732666" />
		<Joint Type="ShoulderCenter" X="0.0565198436379433" Y="0.507865786552429" Z="2.55600380897522" />
		<Joint Type="Head" X="0.0370473526418209" Y="0.65552020072937" Z="2.5599365234375" />
		<Joint Type="ShoulderLeft" X="-0.0887423530220985" Y="0.40502542257309" Z="2.55557537078857" />
		<Joint Type="ElbowLeft" X="-0.111830279231071" Y="0.204228579998016" Z="2.52163648605347" />
		<Joint Type="WristLeft" X="-0.124611422419548" Y="0.0571556985378265" Z="2.46259522438049" />
		<Joint Type="HandLeft" X="-0.127895355224609" Y="0.0361306704580784" Z="2.45527219772339" />
		<Joint Type="ShoulderRight" X="0.163132503628731" Y="0.401294410228729" Z="2.52478528022766" />
		<Joint Type="ElbowRight" X="0.182839706540108" Y="0.236783728003502" Z="2.45670676231384" />
		<Joint Type="WristRight" X="0.165001317858696" Y="0.151313453912735" Z="2.31795430183411" />
		<Joint Type="HandRight" X="0.143254578113556" Y="0.106121018528938" Z="2.2819561958313" />
		<Joint Type="HipLeft" X="-0.0138514433056116" Y="0.148106575012207" Z="2.51199460029602" />
		<Joint Type="KneeLeft" X="0.022948382422328" Y="-0.129681780934334" Z="2.52921009063721" />
		<Joint Type="AnkleLeft" X="0.00497223157435656" Y="-0.377681970596313" Z="2.54326677322388" />
		<Joint Type="FootLeft" X="-0.0124087696895003" Y="-0.419047743082047" Z="2.51459932327271" />
		<Joint Type="HipRight" X="0.0990601778030396" Y="0.154387474060059" Z="2.50450587272644" />
		<Joint Type="KneeRight" X="0.0869916528463364" Y="-0.146797865629196" Z="2.53621864318848" />
		<Joint Type="AnkleRight" X="0.0929434299468994" Y="-0.369040966033936" Z="2.51355195045471" />
		<Joint Type="FootRight" X="0.0766685158014297" Y="-0.41615042090416" Z="2.48391819000244" />
	</BodyPosture>
	<BodyPosture Time="35221940.0603" Joints="20">
		<Joint Type="HipCenter" X="0.052944403141737" Y="0.206449493765831" Z="2.5121476650238" />
		<Joint Type="Spine" X="0.0565558969974518" Y="0.252458274364471" Z="2.550532579422" />
		<Joint Type="ShoulderCenter" X="0.0628096461296082" Y="0.517828762531281" Z="2.55573749542236" />
		<Joint Type="Head" X="0.0482540614902973" Y="0.656568586826324" Z="2.55830597877502" />
		<Joint Type="ShoulderLeft" X="-0.0763306468725204" Y="0.404806554317474" Z="2.54251646995544" />
		<Joint Type="ElbowLeft" X="-0.10009153932333" Y="0.201635047793388" Z="2.52038955688477" />
		<Joint Type="WristLeft" X="-0.0997707918286324" Y="0.0542443990707397" Z="2.46064829826355" />
		<Joint Type="HandLeft" X="-0.106038741767406" Y="0.0281115919351578" Z="2.46429562568665" />
		<Joint Type="ShoulderRight" X="0.172767877578735" Y="0.40319237112999" Z="2.5232834815979" />
		<Joint Type="ElbowRight" X="0.200631365180016" Y="0.250496387481689" Z="2.5138680934906" />
		<Joint Type="WristRight" X="0.21904544532299" Y="0.234296545386314" Z="2.33491826057434" />
		<Joint Type="HandRight" X="0.211977034807205" Y="0.200581967830658" Z="2.29863047599792" />
		<Joint Type="HipLeft" X="-0.00492446357384324" Y="0.145966768264771" Z="2.5033586025238" />
		<Joint Type="KneeLeft" X="0.0394724756479263" Y="-0.151490584015846" Z="2.53359198570251" />
		<Joint Type="AnkleLeft" X="0.0215794909745455" Y="-0.379110515117645" Z="2.54457688331604" />
		<Joint Type="FootLeft" X="0.00500077987089753" Y="-0.418436050415039" Z="2.50272130966187" />
		<Joint Type="HipRight" X="0.109202980995178" Y="0.156890124082565" Z="2.50058031082153" />
		<Joint Type="KneeRight" X="0.0865001380443573" Y="-0.144517004489899" Z="2.53426170349121" />
		<Joint Type="AnkleRight" X="0.0896531790494919" Y="-0.371431082487106" Z="2.51658058166504" />
		<Joint Type="FootRight" X="0.0683444365859032" Y="-0.419295728206635" Z="2.4907648563385" />
	</BodyPosture>
	<BodyPosture Time="35222049.2605" Joints="20">
		<Joint Type="HipCenter" X="0.0551945865154266" Y="0.212679803371429" Z="2.50893068313599" />
		<Joint Type="Spine" X="0.0609304942190647" Y="0.257273584604263" Z="2.54894232749939" />
		<Joint Type="ShoulderCenter" X="0.0676998943090439" Y="0.520540118217468" Z="2.55391621589661" />
		<Joint Type="Head" X="0.0588775463402271" Y="0.657124519348145" Z="2.55458545684814" />
		<Joint Type="ShoulderLeft" X="-0.0722294896841049" Y="0.406111389398575" Z="2.54062700271606" />
		<Joint Type="ElbowLeft" X="-0.0916092768311501" Y="0.211090847849846" Z="2.5264139175415" />
		<Joint Type="WristLeft" X="-0.0969356000423431" Y="0.0590109676122665" Z="2.48421883583069" />
		<Joint Type="HandLeft" X="-0.0980782359838486" Y="0.0370537117123604" Z="2.47622632980347" />
		<Joint Type="ShoulderRight" X="0.181262940168381" Y="0.410025835037231" Z="2.51258492469788" />
		<Joint Type="ElbowRight" X="0.258506804704666" Y="0.303287088871002" Z="2.41027426719666" />
		<Joint Type="WristRight" X="0.26261842250824" Y="0.434357941150665" Z="2.31662130355835" />
		<Joint Type="HandRight" X="0.262962520122528" Y="0.469362437725067" Z="2.31710147857666" />
		<Joint Type="HipLeft" X="-0.00415087630972266" Y="0.155785411596298" Z="2.50054144859314" />
		<Joint Type="KneeLeft" X="0.0455404445528984" Y="-0.150233507156372" Z="2.53625512123108" />
		<Joint Type="AnkleLeft" X="0.0397982634603977" Y="-0.38033601641655" Z="2.51775121688843" />
		<Joint Type="FootLeft" X="0.0484175458550453" Y="-0.422104030847549" Z="2.4753954410553" />
		<Joint Type="HipRight" X="0.110978737473488" Y="0.159176498651505" Z="2.49576497077942" />
		<Joint Type="KneeRight" X="0.078662320971489" Y="-0.145929723978043" Z="2.53593349456787" />
		<Joint Type="AnkleRight" X="0.0820687636733055" Y="-0.380004972219467" Z="2.51527333259583" />
		<Joint Type="FootRight" X="0.0683034434914589" Y="-0.421783149242401" Z="2.48528170585632" />
	</BodyPosture>
	<BodyPosture Time="35222189.6608" Joints="20">
		<Joint Type="HipCenter" X="0.0528652593493462" Y="0.215410932898521" Z="2.50611782073975" />
		<Joint Type="Spine" X="0.0598850883543491" Y="0.259270817041397" Z="2.54738020896912" />
		<Joint Type="ShoulderCenter" X="0.0704135522246361" Y="0.522815108299255" Z="2.55530667304993" />
		<Joint Type="Head" X="0.059986986219883" Y="0.656737923622131" Z="2.55228281021118" />
		<Joint Type="ShoulderLeft" X="-0.0721919313073158" Y="0.406397491693497" Z="2.54073858261108" />
		<Joint Type="ElbowLeft" X="-0.0935888662934303" Y="0.2119270414114" Z="2.52797818183899" />
		<Joint Type="WristLeft" X="-0.104078687727451" Y="0.0610584914684296" Z="2.48164987564087" />
		<Joint Type="HandLeft" X="-0.102015145123005" Y="0.0373344495892525" Z="2.47284722328186" />
		<Joint Type="ShoulderRight" X="0.178131014108658" Y="0.412196815013886" Z="2.51264810562134" />
		<Joint Type="ElbowRight" X="0.247013971209526" Y="0.314342170953751" Z="2.39365029335022" />
		<Joint Type="WristRight" X="0.214681714773178" Y="0.387630105018616" Z="2.25032114982605" />
		<Joint Type="HandRight" X="0.205954045057297" Y="0.400299549102783" Z="2.22219681739807" />
		<Joint Type="HipLeft" X="-0.00753938034176826" Y="0.160621672868729" Z="2.49726676940918" />
		<Joint Type="KneeLeft" X="0.0491616018116474" Y="-0.151370316743851" Z="2.53902077674866" />
		<Joint Type="AnkleLeft" X="0.0405300743877888" Y="-0.379683524370193" Z="2.51646041870117" />
		<Joint Type="FootLeft" X="0.0539902746677399" Y="-0.423692345619202" Z="2.47562789916992" />
		<Joint Type="HipRight" X="0.106358274817467" Y="0.160389736294746" Z="2.4923255443573" />
		<Joint Type="KneeRight" X="0.0803132206201553" Y="-0.144287317991257" Z="2.53902959823608" />
		<Joint Type="AnkleRight" X="0.0817408040165901" Y="-0.380512744188309" Z="2.51574039459229" />
		<Joint Type="FootRight" X="0.0705131888389587" Y="-0.422600984573364" Z="2.48513793945313" />
	</BodyPosture>
	<BodyPosture Time="35222283.2609" Joints="20">
		<Joint Type="HipCenter" X="0.0524275563657284" Y="0.213251888751984" Z="2.50627160072327" />
		<Joint Type="Spine" X="0.0556351207196712" Y="0.257022500038147" Z="2.54823994636536" />
		<Joint Type="ShoulderCenter" X="0.0639327988028526" Y="0.517659246921539" Z="2.55760765075684" />
		<Joint Type="Head" X="0.0554036572575569" Y="0.655523419380188" Z="2.54965376853943" />
		<Joint Type="ShoulderLeft" X="-0.0740574523806572" Y="0.405569344758987" Z="2.54140210151672" />
		<Joint Type="ElbowLeft" X="-0.0998379662632942" Y="0.205581247806549" Z="2.5237865447998" />
		<Joint Type="WristLeft" X="-0.10897970944643" Y="0.054718866944313" Z="2.47711229324341" />
		<Joint Type="HandLeft" X="-0.107393130660057" Y="0.0324804075062275" Z="2.46791315078735" />
		<Joint Type="ShoulderRight" X="0.179882347583771" Y="0.408740192651749" Z="2.53669095039368" />
		<Joint Type="ElbowRight" X="0.198264509439468" Y="0.254447281360626" Z="2.51047968864441" />
		<Joint Type="WristRight" X="0.192305371165276" Y="0.176732510328293" Z="2.36588764190674" />
		<Joint Type="HandRight" X="0.182286739349365" Y="0.154564738273621" Z="2.35083866119385" />
		<Joint Type="HipLeft" X="-0.00682401703670621" Y="0.159945994615555" Z="2.49639821052551" />
		<Joint Type="KneeLeft" X="0.0545939281582832" Y="-0.167858213186264" Z="2.54628229141235" />
		<Joint Type="AnkleLeft" X="0.0414495319128037" Y="-0.378775894641876" Z="2.51568531990051" />
		<Joint Type="FootLeft" X="0.059041827917099" Y="-0.425667643547058" Z="2.47444009780884" />
		<Joint Type="HipRight" X="0.107057362794876" Y="0.154034867882729" Z="2.49472641944885" />
		<Joint Type="KneeRight" X="0.0820852071046829" Y="-0.145123079419136" Z="2.54283213615417" />
		<Joint Type="AnkleRight" X="0.0814157053828239" Y="-0.380893856287003" Z="2.51629900932312" />
		<Joint Type="FootRight" X="0.0723148956894875" Y="-0.422791391611099" Z="2.48475098609924" />
	</BodyPosture>
	<BodyPosture Time="35222423.6612" Joints="20">
		<Joint Type="HipCenter" X="0.054244339466095" Y="0.21350172162056" Z="2.51133012771606" />
		<Joint Type="Spine" X="0.0554726719856262" Y="0.257670819759369" Z="2.55160522460938" />
		<Joint Type="ShoulderCenter" X="0.062356524169445" Y="0.516630172729492" Z="2.55585861206055" />
		<Joint Type="Head" X="0.0534791052341461" Y="0.656085014343262" Z="2.54882574081421" />
		<Joint Type="ShoulderLeft" X="-0.0746824890375137" Y="0.404789298772812" Z="2.54014301300049" />
		<Joint Type="ElbowLeft" X="-0.100379675626755" Y="0.205289646983147" Z="2.52331614494324" />
		<Joint Type="WristLeft" X="-0.106784038245678" Y="0.0547007322311401" Z="2.47498536109924" />
		<Joint Type="HandLeft" X="-0.105595208704472" Y="0.0294798910617828" Z="2.46408367156982" />
		<Joint Type="ShoulderRight" X="0.180030882358551" Y="0.411794126033783" Z="2.54272651672363" />
		<Joint Type="ElbowRight" X="0.205971330404282" Y="0.266574561595917" Z="2.57231855392456" />
		<Joint Type="WristRight" X="0.229721426963806" Y="0.204020172357559" Z="2.42078971862793" />
		<Joint Type="HandRight" X="0.226301610469818" Y="0.16810704767704" Z="2.39284372329712" />
		<Joint Type="HipLeft" X="-0.00525836087763309" Y="0.159645393490791" Z="2.49791836738586" />
		<Joint Type="KneeLeft" X="0.0693665221333504" Y="-0.169005706906319" Z="2.54277944564819" />
		<Joint Type="AnkleLeft" X="0.0160366296768188" Y="-0.361300110816956" Z="2.50010657310486" />
		<Joint Type="FootLeft" X="0.0541245639324188" Y="-0.418080300092697" Z="2.47748994827271" />
		<Joint Type="HipRight" X="0.111832357943058" Y="0.153682231903076" Z="2.51083970069885" />
		<Joint Type="KneeRight" X="0.0828165709972382" Y="-0.147203609347343" Z="2.54728937149048" />
		<Joint Type="AnkleRight" X="0.0812484323978424" Y="-0.38126865029335" Z="2.51642227172852" />
		<Joint Type="FootRight" X="0.0711376368999481" Y="-0.422012686729431" Z="2.48369646072388" />
	</BodyPosture>
	<BodyPosture Time="35222517.2613" Joints="20">
		<Joint Type="HipCenter" X="0.0597909800708294" Y="0.21374449133873" Z="2.52466511726379" />
		<Joint Type="Spine" X="0.0570802316069603" Y="0.258729040622711" Z="2.56275057792664" />
		<Joint Type="ShoulderCenter" X="0.0607492551207542" Y="0.515032827854156" Z="2.55657458305359" />
		<Joint Type="Head" X="0.0546545423567295" Y="0.655232787132263" Z="2.54710125923157" />
		<Joint Type="ShoulderLeft" X="-0.0747453942894936" Y="0.404226332902908" Z="2.53880453109741" />
		<Joint Type="ElbowLeft" X="-0.100233919918537" Y="0.203280121088028" Z="2.52176713943481" />
		<Joint Type="WristLeft" X="-0.105649009346962" Y="0.0521296858787537" Z="2.47556328773499" />
		<Joint Type="HandLeft" X="-0.101937368512154" Y="0.0232684426009655" Z="2.47199106216431" />
		<Joint Type="ShoulderRight" X="0.182064563035965" Y="0.408165574073792" Z="2.55562496185303" />
		<Joint Type="ElbowRight" X="0.207944482564926" Y="0.260924100875854" Z="2.57882189750671" />
		<Joint Type="WristRight" X="0.26204976439476" Y="0.310999184846878" Z="2.40625667572021" />
		<Joint Type="HandRight" X="0.278637051582336" Y="0.325620859861374" Z="2.36633896827698" />
		<Joint Type="HipLeft" X="0.000625412445515394" Y="0.159773126244545" Z="2.50778889656067" />
		<Joint Type="KneeLeft" X="0.0196688491851091" Y="-0.0912940949201584" Z="2.51492810249329" />
		<Joint Type="AnkleLeft" X="0.0399942919611931" Y="-0.361655533313751" Z="2.5142240524292" />
		<Joint Type="FootLeft" X="0.0577952116727829" Y="-0.420922875404358" Z="2.47739577293396" />
		<Joint Type="HipRight" X="0.120266959071159" Y="0.151979446411133" Z="2.5288519859314" />
		<Joint Type="KneeRight" X="0.0832371562719345" Y="-0.144550785422325" Z="2.55209255218506" />
		<Joint Type="AnkleRight" X="0.0812408551573753" Y="-0.381254285573959" Z="2.51656198501587" />
		<Joint Type="FootRight" X="0.0712325945496559" Y="-0.422030121088028" Z="2.48384737968445" />
	</BodyPosture>
	<BodyPosture Time="35222673.2616" Joints="20">
		<Joint Type="HipCenter" X="0.0652425065636635" Y="0.213275521993637" Z="2.53255295753479" />
		<Joint Type="Spine" X="0.0607643984258175" Y="0.257625341415405" Z="2.57140517234802" />
		<Joint Type="ShoulderCenter" X="0.0617813281714916" Y="0.510718703269959" Z="2.56394124031067" />
		<Joint Type="Head" X="0.0603070370852947" Y="0.649543881416321" Z="2.5476541519165" />
		<Joint Type="ShoulderLeft" X="-0.0698565989732742" Y="0.399639964103699" Z="2.5336971282959" />
		<Joint Type="ElbowLeft" X="-0.0951220765709877" Y="0.20262648165226" Z="2.51873803138733" />
		<Joint Type="WristLeft" X="-0.0973886325955391" Y="0.0498979985713959" Z="2.47952151298523" />
		<Joint Type="HandLeft" X="-0.0985011160373688" Y="0.0208920780569315" Z="2.47538471221924" />
		<Joint Type="ShoulderRight" X="0.179976016283035" Y="0.415211021900177" Z="2.5616307258606" />
		<Joint Type="ElbowRight" X="0.228375196456909" Y="0.273832976818085" Z="2.49566531181335" />
		<Joint Type="WristRight" X="0.225171953439713" Y="0.359634935855865" Z="2.35599446296692" />
		<Joint Type="HandRight" X="0.223146960139275" Y="0.362741887569427" Z="2.35508680343628" />
		<Joint Type="HipLeft" X="0.00759899336844683" Y="0.158841028809547" Z="2.5146176815033" />
		<Joint Type="KneeLeft" X="0.0165847484022379" Y="-0.0928916782140732" Z="2.51998353004456" />
		<Joint Type="AnkleLeft" X="0.0413055494427681" Y="-0.363170266151428" Z="2.51503562927246" />
		<Joint Type="FootLeft" X="0.0581299401819706" Y="-0.421847313642502" Z="2.47683668136597" />
		<Joint Type="HipRight" X="0.125834256410599" Y="0.154916316270828" Z="2.53622674942017" />
		<Joint Type="KneeRight" X="0.0840454623103142" Y="-0.14568230509758" Z="2.55565881729126" />
		<Joint Type="AnkleRight" X="0.0815704166889191" Y="-0.382195174694061" Z="2.51732158660889" />
		<Joint Type="FootRight" X="0.0706066191196442" Y="-0.422189950942993" Z="2.48396039009094" />
	</BodyPosture>
	<BodyPosture Time="35222798.0618" Joints="20">
		<Joint Type="HipCenter" X="0.0650422945618629" Y="0.213145226240158" Z="2.53279590606689" />
		<Joint Type="Spine" X="0.0597969852387905" Y="0.257034629583359" Z="2.57181978225708" />
		<Joint Type="ShoulderCenter" X="0.063932366669178" Y="0.509503841400146" Z="2.56758213043213" />
		<Joint Type="Head" X="0.0635192096233368" Y="0.649823665618896" Z="2.55349922180176" />
		<Joint Type="ShoulderLeft" X="-0.065383069217205" Y="0.397944420576096" Z="2.53130888938904" />
		<Joint Type="ElbowLeft" X="-0.0902670323848724" Y="0.201858758926392" Z="2.51297855377197" />
		<Joint Type="WristLeft" X="-0.0880125686526299" Y="0.0495536327362061" Z="2.47163128852844" />
		<Joint Type="HandLeft" X="-0.0910065323114395" Y="0.0185953788459301" Z="2.46368360519409" />
		<Joint Type="ShoulderRight" X="0.185682445764542" Y="0.413424760103226" Z="2.56667757034302" />
		<Joint Type="ElbowRight" X="0.202908754348755" Y="0.271742522716522" Z="2.47641968727112" />
		<Joint Type="WristRight" X="0.150068491697311" Y="0.188181683421135" Z="2.34637022018433" />
		<Joint Type="HandRight" X="0.138524293899536" Y="0.149533793330193" Z="2.29962396621704" />
		<Joint Type="HipLeft" X="0.00706951599568129" Y="0.159214556217194" Z="2.51548337936401" />
		<Joint Type="KneeLeft" X="-0.00430178083479404" Y="-0.0953106284141541" Z="2.524169921875" />
		<Joint Type="AnkleLeft" X="0.0413579493761063" Y="-0.36305570602417" Z="2.51509189605713" />
		<Joint Type="FootLeft" X="0.0580058731138706" Y="-0.421234011650085" Z="2.47606635093689" />
		<Joint Type="HipRight" X="0.123707234859467" Y="0.154146134853363" Z="2.5337119102478" />
		<Joint Type="KneeRight" X="0.0846671313047409" Y="-0.146096080541611" Z="2.55667281150818" />
		<Joint Type="AnkleRight" X="0.0823109522461891" Y="-0.382135599851608" Z="2.51766586303711" />
		<Joint Type="FootRight" X="0.0709267258644104" Y="-0.421720534563065" Z="2.48396134376526" />
	</BodyPosture>
	<BodyPosture Time="35222922.862" Joints="20">
		<Joint Type="HipCenter" X="0.0671060606837273" Y="0.210392326116562" Z="2.53000831604004" />
		<Joint Type="Spine" X="0.0618517696857452" Y="0.254194766283035" Z="2.5703239440918" />
		<Joint Type="ShoulderCenter" X="0.0661735758185387" Y="0.507153987884521" Z="2.56843590736389" />
		<Joint Type="Head" X="0.0659658536314964" Y="0.646778345108032" Z="2.55478692054749" />
		<Joint Type="ShoulderLeft" X="-0.0599506013095379" Y="0.396184802055359" Z="2.52847647666931" />
		<Joint Type="ElbowLeft" X="-0.0763929635286331" Y="0.199492901563644" Z="2.488520860672" />
		<Joint Type="WristLeft" X="-0.0631375759840012" Y="0.0508769601583481" Z="2.43467283248901" />
		<Joint Type="HandLeft" X="-0.0543160960078239" Y="0.0158451572060585" Z="2.43654799461365" />
		<Joint Type="ShoulderRight" X="0.190607726573944" Y="0.404802083969116" Z="2.56436109542847" />
		<Joint Type="ElbowRight" X="0.214234739542007" Y="0.219162747263908" Z="2.52870345115662" />
		<Joint Type="WristRight" X="0.164122343063354" Y="0.0577978417277336" Z="2.46511840820313" />
		<Joint Type="HandRight" X="0.151138156652451" Y="0.0143883675336838" Z="2.45969295501709" />
		<Joint Type="HipLeft" X="0.0101557401940227" Y="0.159572556614876" Z="2.51267504692078" />
		<Joint Type="KneeLeft" X="-0.000643896870315075" Y="-0.0919517129659653" Z="2.5199613571167" />
		<Joint Type="AnkleLeft" X="0.0463235192000866" Y="-0.359249830245972" Z="2.51570272445679" />
		<Joint Type="FootLeft" X="0.0584049448370934" Y="-0.418935805559158" Z="2.47728276252747" />
		<Joint Type="HipRight" X="0.125236928462982" Y="0.146932601928711" Z="2.5274875164032" />
		<Joint Type="KneeRight" X="0.0816075876355171" Y="-0.151151806116104" Z="2.55609178543091" />
		<Joint Type="AnkleRight" X="0.0835974216461182" Y="-0.38379117846489" Z="2.517826795578" />
		<Joint Type="FootRight" X="0.0706196203827858" Y="-0.422313451766968" Z="2.48347616195679" />
	</BodyPosture>
	<BodyPosture Time="35223047.6623" Joints="20">
		<Joint Type="HipCenter" X="0.08236363530159" Y="0.21461683511734" Z="2.54009056091309" />
		<Joint Type="Spine" X="0.073101282119751" Y="0.258602857589722" Z="2.57637810707092" />
		<Joint Type="ShoulderCenter" X="0.070886068046093" Y="0.506076753139496" Z="2.56283688545227" />
		<Joint Type="Head" X="0.0710759311914444" Y="0.647428095340729" Z="2.5505998134613" />
		<Joint Type="ShoulderLeft" X="-0.0501661971211433" Y="0.396125555038452" Z="2.52333426475525" />
		<Joint Type="ElbowLeft" X="-0.0660724341869354" Y="0.1949622631073" Z="2.47182321548462" />
		<Joint Type="WristLeft" X="-0.0542300306260586" Y="0.043233260512352" Z="2.4298050403595" />
		<Joint Type="HandLeft" X="-0.0476075485348701" Y="0.0175940096378326" Z="2.43351054191589" />
		<Joint Type="ShoulderRight" X="0.205214858055115" Y="0.402053117752075" Z="2.57109260559082" />
		<Joint Type="ElbowRight" X="0.240707099437714" Y="0.209241211414337" Z="2.56056928634644" />
		<Joint Type="WristRight" X="0.236948534846306" Y="0.056454062461853" Z="2.52177715301514" />
		<Joint Type="HandRight" X="0.239294618368149" Y="-0.00398222357034683" Z="2.53418755531311" />
		<Joint Type="HipLeft" X="0.0258673429489136" Y="0.162245243787766" Z="2.52283573150635" />
		<Joint Type="KneeLeft" X="0.0181782208383083" Y="-0.0930474549531937" Z="2.52668380737305" />
		<Joint Type="AnkleLeft" X="0.0489562973380089" Y="-0.363027155399323" Z="2.51506400108337" />
		<Joint Type="FootLeft" X="0.058618389070034" Y="-0.421847373247147" Z="2.47468209266663" />
		<Joint Type="HipRight" X="0.145433202385902" Y="0.151054859161377" Z="2.54694128036499" />
		<Joint Type="KneeRight" X="0.082445926964283" Y="-0.150328144431114" Z="2.55710458755493" />
		<Joint Type="AnkleRight" X="0.0848599821329117" Y="-0.384078025817871" Z="2.51758241653442" />
		<Joint Type="FootRight" X="0.0736590921878815" Y="-0.423025965690613" Z="2.4830915927887" />
	</BodyPosture>
	<BodyPosture Time="35223250.4626" Joints="20">
		<Joint Type="HipCenter" X="0.0879901871085167" Y="0.214757040143013" Z="2.54103183746338" />
		<Joint Type="Spine" X="0.0783660262823105" Y="0.259311884641647" Z="2.57513093948364" />
		<Joint Type="ShoulderCenter" X="0.0741772428154945" Y="0.505094707012177" Z="2.55995917320251" />
		<Joint Type="Head" X="0.073136068880558" Y="0.647275388240814" Z="2.54869318008423" />
		<Joint Type="ShoulderLeft" X="-0.0452087484300137" Y="0.396801263093948" Z="2.52095103263855" />
		<Joint Type="ElbowLeft" X="-0.0622673779726028" Y="0.192948281764984" Z="2.46595692634583" />
		<Joint Type="WristLeft" X="-0.0465032681822777" Y="0.0412931889295578" Z="2.42526268959045" />
		<Joint Type="HandLeft" X="-0.0398363955318928" Y="-0.00385097041726112" Z="2.42512989044189" />
		<Joint Type="ShoulderRight" X="0.209479764103889" Y="0.40307879447937" Z="2.57437539100647" />
		<Joint Type="ElbowRight" X="0.254598945379257" Y="0.214139610528946" Z="2.57510304450989" />
		<Joint Type="WristRight" X="0.290334165096283" Y="0.0633019655942917" Z="2.55243158340454" />
		<Joint Type="HandRight" X="0.32565450668335" Y="0.0157599374651909" Z="2.56986904144287" />
		<Joint Type="HipLeft" X="0.0333989821374416" Y="0.160221800208092" Z="2.52367210388184" />
		<Joint Type="KneeLeft" X="0.0224240962415934" Y="-0.0974549725651741" Z="2.52880358695984" />
		<Joint Type="AnkleLeft" X="0.0510859042406082" Y="-0.367745131254196" Z="2.51467490196228" />
		<Joint Type="FootLeft" X="0.0611917898058891" Y="-0.425209909677505" Z="2.47249865531921" />
		<Joint Type="HipRight" X="0.149600729346275" Y="0.152644753456116" Z="2.54835247993469" />
		<Joint Type="KneeRight" X="0.0831031203269959" Y="-0.149655789136887" Z="2.55651807785034" />
		<Joint Type="AnkleRight" X="0.08443533629179" Y="-0.384464025497437" Z="2.51726865768433" />
		<Joint Type="FootRight" X="0.0733564645051956" Y="-0.423441827297211" Z="2.4827778339386" />
	</BodyPosture>
	<BodyPosture Time="35223359.6628" Joints="20">
		<Joint Type="HipCenter" X="0.0909551605582237" Y="0.214656516909599" Z="2.53315305709839" />
		<Joint Type="Spine" X="0.0829842463135719" Y="0.258920401334763" Z="2.56760501861572" />
		<Joint Type="ShoulderCenter" X="0.0812836587429047" Y="0.50429892539978" Z="2.55608248710632" />
		<Joint Type="Head" X="0.0793457627296448" Y="0.649169564247131" Z="2.54315042495728" />
		<Joint Type="ShoulderLeft" X="-0.0415069833397865" Y="0.39773952960968" Z="2.52081060409546" />
		<Joint Type="ElbowLeft" X="-0.0614660046994686" Y="0.198033645749092" Z="2.46982312202454" />
		<Joint Type="WristLeft" X="-0.0491246320307255" Y="0.0466388314962387" Z="2.42635416984558" />
		<Joint Type="HandLeft" X="-0.0454864278435707" Y="0.00185315310955048" Z="2.43431401252747" />
		<Joint Type="ShoulderRight" X="0.218895331025124" Y="0.403520703315735" Z="2.5700798034668" />
		<Joint Type="ElbowRight" X="0.260937422513962" Y="0.215760007500648" Z="2.57535362243652" />
		<Joint Type="WristRight" X="0.270564019680023" Y="0.0665876716375351" Z="2.52236533164978" />
		<Joint Type="HandRight" X="0.286309599876404" Y="0.00689344853162766" Z="2.52292799949646" />
		<Joint Type="HipLeft" X="0.034845806658268" Y="0.157583475112915" Z="2.51555752754211" />
		<Joint Type="KneeLeft" X="0.0635673850774765" Y="-0.156028792262077" Z="2.55105423927307" />
		<Joint Type="AnkleLeft" X="0.0525128059089184" Y="-0.381683230400085" Z="2.51508283615112" />
		<Joint Type="FootLeft" X="0.0613266490399837" Y="-0.426365107297897" Z="2.47162508964539" />
		<Joint Type="HipRight" X="0.151862218976021" Y="0.153670161962509" Z="2.53656435012817" />
		<Joint Type="KneeRight" X="0.0844761952757835" Y="-0.150139316916466" Z="2.55540800094604" />
		<Joint Type="AnkleRight" X="0.0867606550455093" Y="-0.386758983135223" Z="2.51758980751038" />
		<Joint Type="FootRight" X="0.075811505317688" Y="-0.425966948270798" Z="2.48332548141479" />
	</BodyPosture>
	<BodyPosture Time="35223468.863" Joints="20">
		<Joint Type="HipCenter" X="0.0938618704676628" Y="0.214128494262695" Z="2.52846670150757" />
		<Joint Type="Spine" X="0.0865744426846504" Y="0.257762998342514" Z="2.56394910812378" />
		<Joint Type="ShoulderCenter" X="0.0847223028540611" Y="0.502142071723938" Z="2.55445051193237" />
		<Joint Type="Head" X="0.0850979685783386" Y="0.645301699638367" Z="2.54224228858948" />
		<Joint Type="ShoulderLeft" X="-0.0393810383975506" Y="0.397958666086197" Z="2.52179479598999" />
		<Joint Type="ElbowLeft" X="-0.0604968965053558" Y="0.20103856921196" Z="2.47616243362427" />
		<Joint Type="WristLeft" X="-0.0590531416237354" Y="0.0484996885061264" Z="2.43576431274414" />
		<Joint Type="HandLeft" X="-0.0665641278028488" Y="0.0132482908666134" Z="2.46211552619934" />
		<Joint Type="ShoulderRight" X="0.22264452278614" Y="0.400310397148132" Z="2.56621170043945" />
		<Joint Type="ElbowRight" X="0.241006299853325" Y="0.208863392472267" Z="2.54377484321594" />
		<Joint Type="WristRight" X="0.236206978559494" Y="0.0596615225076675" Z="2.49006843566895" />
		<Joint Type="HandRight" X="0.229984998703003" Y="0.00203230604529381" Z="2.46880435943604" />
		<Joint Type="HipLeft" X="0.0374687872827053" Y="0.157346427440643" Z="2.51093864440918" />
		<Joint Type="KneeLeft" X="0.062422338873148" Y="-0.156974703073502" Z="2.55086374282837" />
		<Joint Type="AnkleLeft" X="0.053129255771637" Y="-0.382168591022491" Z="2.5148503780365" />
		<Joint Type="FootLeft" X="0.0611308366060257" Y="-0.426251739263535" Z="2.4720618724823" />
		<Joint Type="HipRight" X="0.154569983482361" Y="0.152738586068153" Z="2.530113697052" />
		<Joint Type="KneeRight" X="0.0824134647846222" Y="-0.152720928192139" Z="2.55390930175781" />
		<Joint Type="AnkleRight" X="0.0854082554578781" Y="-0.386525869369507" Z="2.51663255691528" />
		<Joint Type="FootRight" X="0.0757595151662827" Y="-0.427384585142136" Z="2.48394131660461" />
	</BodyPosture>
	<BodyPosture Time="35223624.8633" Joints="20">
		<Joint Type="HipCenter" X="0.0924778282642365" Y="0.211844205856323" Z="2.52319431304932" />
		<Joint Type="Spine" X="0.0867522284388542" Y="0.255492210388184" Z="2.56098365783691" />
		<Joint Type="ShoulderCenter" X="0.088651679456234" Y="0.501905679702759" Z="2.55511379241943" />
		<Joint Type="Head" X="0.0918023362755775" Y="0.646025955677032" Z="2.54040193557739" />
		<Joint Type="ShoulderLeft" X="-0.0368412993848324" Y="0.398668378591537" Z="2.52324986457825" />
		<Joint Type="ElbowLeft" X="-0.0613018684089184" Y="0.207735359668732" Z="2.48675799369812" />
		<Joint Type="WristLeft" X="-0.0652022734284401" Y="0.0561923235654831" Z="2.44190835952759" />
		<Joint Type="HandLeft" X="-0.0700312852859497" Y="0.0171869769692421" Z="2.46231031417847" />
		<Joint Type="ShoulderRight" X="0.223869770765305" Y="0.400466769933701" Z="2.56415581703186" />
		<Joint Type="ElbowRight" X="0.234865039587021" Y="0.219554618000984" Z="2.52564167976379" />
		<Joint Type="WristRight" X="0.211623579263687" Y="0.0799813270568848" Z="2.45103001594543" />
		<Joint Type="HandRight" X="0.181642815470695" Y="0.0346554256975651" Z="2.42171549797058" />
		<Joint Type="HipLeft" X="0.0347561724483967" Y="0.15452054142952" Z="2.50682163238525" />
		<Joint Type="KneeLeft" X="0.0638146474957466" Y="-0.168669775128365" Z="2.55325412750244" />
		<Joint Type="AnkleLeft" X="0.0530280545353889" Y="-0.382185280323029" Z="2.51482796669006" />
		<Joint Type="FootLeft" X="0.0615205839276314" Y="-0.426303863525391" Z="2.47271370887756" />
		<Joint Type="HipRight" X="0.150130480527878" Y="0.152474865317345" Z="2.51900601387024" />
		<Joint Type="KneeRight" X="0.083831712603569" Y="-0.152524441480637" Z="2.55369663238525" />
		<Joint Type="AnkleRight" X="0.0852554142475128" Y="-0.386736690998077" Z="2.51695489883423" />
		<Joint Type="FootRight" X="0.0749597623944283" Y="-0.427074402570724" Z="2.48381018638611" />
	</BodyPosture>
</BodyGesture>
